{"Meta Data": {"1. Information": "Daily Time Series with Splits and Dividend Events", "2. Symbol": "HSY", "3. Last Refreshed": "2025-04-22", "4. Output Size": "Compact", "5. Time Zone": "US/Eastern"}, "Time Series (Daily)": {"2025-04-22": {"1. open": "166.85", "2. high": "168.92", "3. low": "165.74", "4. close": "167.44", "5. adjusted close": "167.44", "6. volume": "1002529", "7. dividend amount": "0.0000", "8. split coefficient": "1.0"}, "2025-04-21": {"1. open": "166.37", "2. high": "166.68", "3. low": "164.72", "4. close": "166.47", "5. adjusted close": "166.47", "6. volume": "743371", "7. dividend amount": "0.0000", "8. split coefficient": "1.0"}, "2025-04-17": {"1. open": "165.86", "2. high": "167.14", "3. low": "162.77", "4. close": "166.59", "5. adjusted close": "166.59", "6. volume": "1120485", "7. dividend amount": "0.0000", "8. split coefficient": "1.0"}, "2025-04-16": {"1. open": "168.66", "2. high": "169.51", "3. low": "163.6211", "4. close": "164.23", "5. adjusted close": "164.23", "6. volume": "1024631", "7. dividend amount": "0.0000", "8. split coefficient": "1.0"}, "2025-04-15": {"1. open": "170.3", "2. high": "171.5", "3. low": "166.72", "4. close": "167.95", "5. adjusted close": "167.95", "6. volume": "1252353", "7. dividend amount": "0.0000", "8. split coefficient": "1.0"}, "2025-04-14": {"1. open": "166.0", "2. high": "171.26", "3. low": "165.58", "4. close": "170.3", "5. adjusted close": "170.3", "6. volume": "1637631", "7. dividend amount": "0.0000", "8. split coefficient": "1.0"}, "2025-04-11": {"1. open": "164.56", "2. high": "166.9", "3. low": "162.65", "4. close": "165.65", "5. adjusted close": "165.65", "6. volume": "1233967", "7. dividend amount": "0.0000", "8. split coefficient": "1.0"}, "2025-04-10": {"1. open": "163.63", "2. high": "166.43", "3. low": "160.89", "4. close": "164.09", "5. adjusted close": "164.09", "6. volume": "1491611", "7. dividend amount": "0.0000", "8. split coefficient": "1.0"}, "2025-04-09": {"1. open": "158.47", "2. high": "166.38", "3. low": "157.07", "4. close": "164.16", "5. adjusted close": "164.16", "6. volume": "1830897", "7. dividend amount": "0.0000", "8. split coefficient": "1.0"}, "2025-04-08": {"1. open": "164.23", "2. high": "166.04", "3. low": "157.4", "4. close": "159.1", "5. adjusted close": "159.1", "6. volume": "1853631", "7. dividend amount": "0.0000", "8. split coefficient": "1.0"}, "2025-04-07": {"1. open": "160.7", "2. high": "165.005", "3. low": "157.0606", "4. close": "162.6", "5. adjusted close": "162.6", "6. volume": "2376850", "7. dividend amount": "0.0000", "8. split coefficient": "1.0"}, "2025-04-04": {"1. open": "168.0", "2. high": "171.58", "3. low": "161.22", "4. close": "162.24", "5. adjusted close": "162.24", "6. volume": "2504606", "7. dividend amount": "0.0000", "8. split coefficient": "1.0"}, "2025-04-03": {"1. open": "163.65", "2. high": "167.48", "3. low": "162.27", "4. close": "166.83", "5. adjusted close": "166.83", "6. volume": "3022273", "7. dividend amount": "0.0000", "8. split coefficient": "1.0"}, "2025-04-02": {"1. open": "169.97", "2. high": "171.25", "3. low": "163.43", "4. close": "163.95", "5. adjusted close": "163.95", "6. volume": "1644914", "7. dividend amount": "0.0000", "8. split coefficient": "1.0"}, "2025-04-01": {"1. open": "171.69", "2. high": "172.195", "3. low": "168.52", "4. close": "169.62", "5. adjusted close": "169.62", "6. volume": "951002", "7. dividend amount": "0.0000", "8. split coefficient": "1.0"}, "2025-03-31": {"1. open": "170.75", "2. high": "172.77", "3. low": "169.35", "4. close": "171.03", "5. adjusted close": "171.03", "6. volume": "1759465", "7. dividend amount": "0.0000", "8. split coefficient": "1.0"}, "2025-03-28": {"1. open": "172.0", "2. high": "173.55", "3. low": "169.23", "4. close": "169.86", "5. adjusted close": "169.86", "6. volume": "1075214", "7. dividend amount": "0.0000", "8. split coefficient": "1.0"}, "2025-03-27": {"1. open": "169.8", "2. high": "171.55", "3. low": "168.01", "4. close": "170.62", "5. adjusted close": "170.62", "6. volume": "754888", "7. dividend amount": "0.0000", "8. split coefficient": "1.0"}, "2025-03-26": {"1. open": "165.09", "2. high": "169.7", "3. low": "165.09", "4. close": "168.52", "5. adjusted close": "168.52", "6. volume": "1123261", "7. dividend amount": "0.0000", "8. split coefficient": "1.0"}, "2025-03-25": {"1. open": "167.54", "2. high": "167.54", "3. low": "164.43", "4. close": "165.23", "5. adjusted close": "165.23", "6. volume": "1409434", "7. dividend amount": "0.0000", "8. split coefficient": "1.0"}, "2025-03-24": {"1. open": "166.85", "2. high": "168.74", "3. low": "164.51", "4. close": "168.01", "5. adjusted close": "168.01", "6. volume": "1475462", "7. dividend amount": "0.0000", "8. split coefficient": "1.0"}, "2025-03-21": {"1. open": "164.26", "2. high": "167.8599", "3. low": "164.26", "4. close": "167.18", "5. adjusted close": "167.18", "6. volume": "3047098", "7. dividend amount": "0.0000", "8. split coefficient": "1.0"}, "2025-03-20": {"1. open": "167.25", "2. high": "167.78", "3. low": "163.7976", "4. close": "164.47", "5. adjusted close": "164.47", "6. volume": "1696752", "7. dividend amount": "0.0000", "8. split coefficient": "1.0"}, "2025-03-19": {"1. open": "167.77", "2. high": "168.55", "3. low": "165.65", "4. close": "167.35", "5. adjusted close": "167.35", "6. volume": "1705170", "7. dividend amount": "0.0000", "8. split coefficient": "1.0"}, "2025-03-18": {"1. open": "170.76", "2. high": "171.7", "3. low": "168.765", "4. close": "169.42", "5. adjusted close": "169.42", "6. volume": "991871", "7. dividend amount": "0.0000", "8. split coefficient": "1.0"}, "2025-03-17": {"1. open": "170.0", "2. high": "172.17", "3. low": "168.85", "4. close": "170.49", "5. adjusted close": "170.49", "6. volume": "997919", "7. dividend amount": "0.0000", "8. split coefficient": "1.0"}, "2025-03-14": {"1. open": "171.59", "2. high": "175.0", "3. low": "170.09", "4. close": "170.22", "5. adjusted close": "170.22", "6. volume": "1357591", "7. dividend amount": "0.0000", "8. split coefficient": "1.0"}, "2025-03-13": {"1. open": "170.59", "2. high": "174.2269", "3. low": "170.59", "4. close": "171.94", "5. adjusted close": "171.94", "6. volume": "1543479", "7. dividend amount": "0.0000", "8. split coefficient": "1.0"}, "2025-03-12": {"1. open": "177.01", "2. high": "177.01", "3. low": "170.65", "4. close": "170.94", "5. adjusted close": "170.94", "6. volume": "2591637", "7. dividend amount": "0.0000", "8. split coefficient": "1.0"}, "2025-03-11": {"1. open": "185.99", "2. high": "186.49", "3. low": "179.22", "4. close": "179.54", "5. adjusted close": "179.54", "6. volume": "2256810", "7. dividend amount": "0.0000", "8. split coefficient": "1.0"}, "2025-03-10": {"1. open": "186.92", "2. high": "193.39", "3. low": "185.71", "4. close": "186.36", "5. adjusted close": "186.36", "6. volume": "2896984", "7. dividend amount": "0.0000", "8. split coefficient": "1.0"}, "2025-03-07": {"1. open": "179.78", "2. high": "189.48", "3. low": "179.615", "4. close": "185.06", "5. adjusted close": "185.06", "6. volume": "2806471", "7. dividend amount": "0.0000", "8. split coefficient": "1.0"}, "2025-03-06": {"1. open": "178.57", "2. high": "180.2775", "3. low": "176.0201", "4. close": "180.01", "5. adjusted close": "180.01", "6. volume": "1015577", "7. dividend amount": "0.0000", "8. split coefficient": "1.0"}, "2025-03-05": {"1. open": "176.33", "2. high": "178.6", "3. low": "175.08", "4. close": "177.03", "5. adjusted close": "177.03", "6. volume": "1186129", "7. dividend amount": "0.0000", "8. split coefficient": "1.0"}, "2025-03-04": {"1. open": "180.95", "2. high": "184.25", "3. low": "176.26", "4. close": "176.38", "5. adjusted close": "176.38", "6. volume": "2605402", "7. dividend amount": "0.0000", "8. split coefficient": "1.0"}, "2025-03-03": {"1. open": "173.0", "2. high": "179.12", "3. low": "173.0", "4. close": "178.5", "5. adjusted close": "178.5", "6. volume": "1790787", "7. dividend amount": "0.0000", "8. split coefficient": "1.0"}, "2025-02-28": {"1. open": "173.79", "2. high": "175.76", "3. low": "171.42", "4. close": "172.71", "5. adjusted close": "172.71", "6. volume": "2540847", "7. dividend amount": "0.0000", "8. split coefficient": "1.0"}, "2025-02-27": {"1. open": "170.74", "2. high": "172.49", "3. low": "169.56", "4. close": "172.34", "5. adjusted close": "172.34", "6. volume": "1464534", "7. dividend amount": "0.0000", "8. split coefficient": "1.0"}, "2025-02-26": {"1. open": "177.53", "2. high": "177.75", "3. low": "170.3878", "4. close": "171.29", "5. adjusted close": "171.29", "6. volume": "3221512", "7. dividend amount": "0.0000", "8. split coefficient": "1.0"}, "2025-02-25": {"1. open": "177.84", "2. high": "181.92", "3. low": "177.01", "4. close": "178.65", "5. adjusted close": "178.65", "6. volume": "2733405", "7. dividend amount": "0.0000", "8. split coefficient": "1.0"}, "2025-02-24": {"1. open": "172.45", "2. high": "179.0", "3. low": "171.4341", "4. close": "177.84", "5. adjusted close": "177.84", "6. volume": "3230978", "7. dividend amount": "0.0000", "8. split coefficient": "1.0"}, "2025-02-21": {"1. open": "166.51", "2. high": "175.29", "3. low": "166.45", "4. close": "172.86", "5. adjusted close": "172.86", "6. volume": "4115420", "7. dividend amount": "0.0000", "8. split coefficient": "1.0"}, "2025-02-20": {"1. open": "163.7", "2. high": "166.8", "3. low": "163.0", "4. close": "166.1", "5. adjusted close": "166.1", "6. volume": "1527071", "7. dividend amount": "0.0000", "8. split coefficient": "1.0"}, "2025-02-19": {"1. open": "163.2", "2. high": "164.13", "3. low": "160.865", "4. close": "163.9", "5. adjusted close": "163.9", "6. volume": "1391979", "7. dividend amount": "0.0000", "8. split coefficient": "1.0"}, "2025-02-18": {"1. open": "155.99", "2. high": "163.8", "3. low": "154.25", "4. close": "162.99", "5. adjusted close": "162.99", "6. volume": "2976893", "7. dividend amount": "0.0000", "8. split coefficient": "1.0"}, "2025-02-14": {"1. open": "160.0", "2. high": "160.875", "3. low": "157.75", "4. close": "157.88", "5. adjusted close": "157.88", "6. volume": "1450515", "7. dividend amount": "1.3700", "8. split coefficient": "1.0"}, "2025-02-13": {"1. open": "157.75", "2. high": "161.09", "3. low": "157.49", "4. close": "160.81", "5. adjusted close": "159.426579591837", "6. volume": "1632531", "7. dividend amount": "0.0000", "8. split coefficient": "1.0"}, "2025-02-12": {"1. open": "156.37", "2. high": "158.33", "3. low": "155.825", "4. close": "158.08", "5. adjusted close": "156.720065306122", "6. volume": "1382853", "7. dividend amount": "0.0000", "8. split coefficient": "1.0"}, "2025-02-11": {"1. open": "153.8", "2. high": "159.405", "3. low": "153.49", "4. close": "158.26", "5. adjusted close": "156.898516797488", "6. volume": "1890954", "7. dividend amount": "0.0000", "8. split coefficient": "1.0"}, "2025-02-10": {"1. open": "155.46", "2. high": "155.8343", "3. low": "153.0", "4. close": "154.47", "5. adjusted close": "153.141121507064", "6. volume": "1614873", "7. dividend amount": "0.0000", "8. split coefficient": "1.0"}, "2025-02-07": {"1. open": "154.06", "2. high": "156.56", "3. low": "153.553895", "4. close": "154.93", "5. adjusted close": "153.597164207221", "6. volume": "2395036", "7. dividend amount": "0.0000", "8. split coefficient": "1.0"}, "2025-02-06": {"1. open": "155.25", "2. high": "156.69", "3. low": "150.51", "4. close": "152.34", "5. adjusted close": "151.029445525903", "6. volume": "4131715", "7. dividend amount": "0.0000", "8. split coefficient": "1.0"}, "2025-02-05": {"1. open": "141.0", "2. high": "146.33", "3. low": "140.13", "4. close": "145.92", "5. adjusted close": "144.66467566719", "6. volume": "3897832", "7. dividend amount": "0.0000", "8. split coefficient": "1.0"}, "2025-02-04": {"1. open": "147.53", "2. high": "147.54", "3. low": "143.9501", "4. close": "144.74", "5. adjusted close": "143.49482700157", "6. volume": "2189568", "7. dividend amount": "0.0000", "8. split coefficient": "1.0"}, "2025-02-03": {"1. open": "148.0", "2. high": "148.98", "3. low": "146.48", "4. close": "147.79", "5. adjusted close": "146.518588383046", "6. volume": "1766275", "7. dividend amount": "0.0000", "8. split coefficient": "1.0"}, "2025-01-31": {"1. open": "150.0", "2. high": "151.65", "3. low": "147.66", "4. close": "149.25", "5. adjusted close": "147.966028257457", "6. volume": "1977514", "7. dividend amount": "0.0000", "8. split coefficient": "1.0"}, "2025-01-30": {"1. open": "150.24", "2. high": "152.21", "3. low": "149.2", "4. close": "152.14", "5. adjusted close": "150.831166091052", "6. volume": "1669659", "7. dividend amount": "0.0000", "8. split coefficient": "1.0"}, "2025-01-29": {"1. open": "150.3", "2. high": "150.55", "3. low": "148.54", "4. close": "149.23", "5. adjusted close": "147.946200313972", "6. volume": "1217296", "7. dividend amount": "0.0000", "8. split coefficient": "1.0"}, "2025-01-28": {"1. open": "153.73", "2. high": "154.2638", "3. low": "149.3", "4. close": "149.73", "5. adjusted close": "148.441898901099", "6. volume": "1539016", "7. dividend amount": "0.0000", "8. split coefficient": "1.0"}, "2025-01-27": {"1. open": "153.28", "2. high": "155.59", "3. low": "152.5001", "4. close": "153.72", "5. adjusted close": "152.397573626374", "6. volume": "2309817", "7. dividend amount": "0.0000", "8. split coefficient": "1.0"}, "2025-01-24": {"1. open": "149.38", "2. high": "151.5597", "3. low": "147.6", "4. close": "150.71", "5. adjusted close": "149.413468131868", "6. volume": "1501467", "7. dividend amount": "0.0000", "8. split coefficient": "1.0"}, "2025-01-23": {"1. open": "150.52", "2. high": "151.5028", "3. low": "148.743884", "4. close": "149.89", "5. adjusted close": "148.60052244898", "6. volume": "1837909", "7. dividend amount": "0.0000", "8. split coefficient": "1.0"}, "2025-01-22": {"1. open": "153.6", "2. high": "153.6099", "3. low": "150.42", "4. close": "151.12", "5. adjusted close": "149.819940973312", "6. volume": "1563502", "7. dividend amount": "0.0000", "8. split coefficient": "1.0"}, "2025-01-21": {"1. open": "153.0", "2. high": "155.1999", "3. low": "152.2", "4. close": "153.57", "5. adjusted close": "152.248864050235", "6. volume": "1744296", "7. dividend amount": "0.0000", "8. split coefficient": "1.0"}, "2025-01-17": {"1. open": "153.47", "2. high": "155.22", "3. low": "152.122", "4. close": "152.87", "5. adjusted close": "151.554886028257", "6. volume": "1937411", "7. dividend amount": "0.0000", "8. split coefficient": "1.0"}, "2025-01-16": {"1. open": "151.0", "2. high": "155.02", "3. low": "150.55", "4. close": "154.02", "5. adjusted close": "152.69499277865", "6. volume": "1973399", "7. dividend amount": "0.0000", "8. split coefficient": "1.0"}, "2025-01-15": {"1. open": "155.31", "2. high": "156.08", "3. low": "150.31", "4. close": "151.75", "5. adjusted close": "150.444521193093", "6. volume": "3584580", "7. dividend amount": "0.0000", "8. split coefficient": "1.0"}, "2025-01-14": {"1. open": "156.61", "2. high": "157.27", "3. low": "154.46", "4. close": "155.31", "5. adjusted close": "153.973895133438", "6. volume": "2179990", "7. dividend amount": "0.0000", "8. split coefficient": "1.0"}, "2025-01-13": {"1. open": "159.17", "2. high": "159.51", "3. low": "156.9", "4. close": "157.28", "5. adjusted close": "155.926947566719", "6. volume": "2731311", "7. dividend amount": "0.0000", "8. split coefficient": "1.0"}, "2025-01-10": {"1. open": "162.2", "2. high": "162.9", "3. low": "156.1", "4. close": "158.2", "5. adjusted close": "156.839032967033", "6. volume": "3028045", "7. dividend amount": "0.0000", "8. split coefficient": "1.0"}, "2025-01-08": {"1. open": "165.0", "2. high": "165.4", "3. low": "159.87", "4. close": "162.22", "5. adjusted close": "160.824449607535", "6. volume": "2833895", "7. dividend amount": "0.0000", "8. split coefficient": "1.0"}, "2025-01-07": {"1. open": "166.7", "2. high": "169.0", "3. low": "165.38", "4. close": "165.52", "5. adjusted close": "164.096060282575", "6. volume": "1303137", "7. dividend amount": "0.0000", "8. split coefficient": "1.0"}, "2025-01-06": {"1. open": "168.44", "2. high": "168.89", "3. low": "165.78", "4. close": "166.74", "5. adjusted close": "165.305564835165", "6. volume": "1387876", "7. dividend amount": "0.0000", "8. split coefficient": "1.0"}, "2025-01-03": {"1. open": "169.03", "2. high": "170.4", "3. low": "167.95", "4. close": "169.03", "5. adjusted close": "167.575864364207", "6. volume": "932666", "7. dividend amount": "0.0000", "8. split coefficient": "1.0"}, "2025-01-02": {"1. open": "171.2", "2. high": "171.28", "3. low": "167.6301", "4. close": "168.79", "5. adjusted close": "167.337929042386", "6. volume": "864572", "7. dividend amount": "0.0000", "8. split coefficient": "1.0"}, "2024-12-31": {"1. open": "168.77", "2. high": "169.9", "3. low": "167.49", "4. close": "169.35", "5. adjusted close": "167.893111459969", "6. volume": "869929", "7. dividend amount": "0.0000", "8. split coefficient": "1.0"}, "2024-12-30": {"1. open": "171.62", "2. high": "171.86", "3. low": "167.52", "4. close": "168.67", "5. adjusted close": "167.218961381476", "6. volume": "1771549", "7. dividend amount": "0.0000", "8. split coefficient": "1.0"}, "2024-12-27": {"1. open": "169.57", "2. high": "172.12", "3. low": "169.51", "4. close": "171.76", "5. adjusted close": "170.282378649921", "6. volume": "1066265", "7. dividend amount": "0.0000", "8. split coefficient": "1.0"}, "2024-12-26": {"1. open": "169.6", "2. high": "172.2732", "3. low": "169.0", "4. close": "170.18", "5. adjusted close": "168.7159711146", "6. volume": "992477", "7. dividend amount": "0.0000", "8. split coefficient": "1.0"}, "2024-12-24": {"1. open": "169.0", "2. high": "170.49", "3. low": "167.96", "4. close": "170.49", "5. adjusted close": "169.023304238619", "6. volume": "429603", "7. dividend amount": "0.0000", "8. split coefficient": "1.0"}, "2024-12-23": {"1. open": "169.3", "2. high": "170.21", "3. low": "166.69", "4. close": "169.0", "5. adjusted close": "167.54612244898", "6. volume": "1172883", "7. dividend amount": "0.0000", "8. split coefficient": "1.0"}, "2024-12-20": {"1. open": "169.21", "2. high": "172.04", "3. low": "168.585", "4. close": "170.26", "5. adjusted close": "168.79528288854", "6. volume": "2535399", "7. dividend amount": "0.0000", "8. split coefficient": "1.0"}, "2024-12-19": {"1. open": "171.59", "2. high": "172.44", "3. low": "168.81", "4. close": "168.94", "5. adjusted close": "167.486638618524", "6. volume": "1930419", "7. dividend amount": "0.0000", "8. split coefficient": "1.0"}, "2024-12-18": {"1. open": "175.5", "2. high": "175.5", "3. low": "171.87", "4. close": "172.46", "5. adjusted close": "170.9763566719", "6. volume": "1837939", "7. dividend amount": "0.0000", "8. split coefficient": "1.0"}, "2024-12-17": {"1. open": "177.84", "2. high": "181.56", "3. low": "176.75", "4. close": "177.63", "5. adjusted close": "176.101880062794", "6. volume": "1834510", "7. dividend amount": "0.0000", "8. split coefficient": "1.0"}, "2024-12-16": {"1. open": "182.1", "2. high": "184.02", "3. low": "177.25", "4. close": "178.2", "5. adjusted close": "176.666976452119", "6. volume": "2241293", "7. dividend amount": "0.0000", "8. split coefficient": "1.0"}, "2024-12-13": {"1. open": "183.39", "2. high": "184.43", "3. low": "181.6901", "4. close": "183.1", "5. adjusted close": "181.524822605965", "6. volume": "1985580", "7. dividend amount": "0.0000", "8. split coefficient": "1.0"}, "2024-12-12": {"1. open": "175.88", "2. high": "184.52", "3. low": "175.75", "4. close": "183.95", "5. adjusted close": "182.367510204082", "6. volume": "3761748", "7. dividend amount": "0.0000", "8. split coefficient": "1.0"}, "2024-12-11": {"1. open": "178.65", "2. high": "183.21", "3. low": "174.28", "4. close": "177.0", "5. adjusted close": "175.477299843014", "6. volume": "6250738", "7. dividend amount": "0.0000", "8. split coefficient": "1.0"}, "2024-12-10": {"1. open": "193.59", "2. high": "196.82", "3. low": "185.95", "4. close": "187.19", "5. adjusted close": "185.579637048666", "6. volume": "5012355", "7. dividend amount": "0.0000", "8. split coefficient": "1.0"}, "2024-12-09": {"1. open": "174.05", "2. high": "208.03", "3. low": "173.61", "4. close": "193.65", "5. adjusted close": "191.984062794348", "6. volume": "14377144", "7. dividend amount": "0.0000", "8. split coefficient": "1.0"}, "2024-12-06": {"1. open": "175.4", "2. high": "177.02", "3. low": "173.78", "4. close": "174.7", "5. adjusted close": "173.197086342229", "6. volume": "2332272", "7. dividend amount": "0.0000", "8. split coefficient": "1.0"}, "2024-12-05": {"1. open": "177.28", "2. high": "177.33", "3. low": "173.05", "4. close": "174.5", "5. adjusted close": "172.998806907378", "6. volume": "1953513", "7. dividend amount": "0.0000", "8. split coefficient": "1.0"}, "2024-12-04": {"1. open": "178.44", "2. high": "185.0", "3. low": "174.35", "4. close": "177.87", "5. adjusted close": "176.339815384615", "6. volume": "4591594", "7. dividend amount": "0.0000", "8. split coefficient": "1.0"}, "2024-12-03": {"1. open": "177.34", "2. high": "181.82", "3. low": "176.22", "4. close": "179.48", "5. adjusted close": "177.935964835165", "6. volume": "3986597", "7. dividend amount": "0.0000", "8. split coefficient": "1.0"}, "2024-12-02": {"1. open": "176.13", "2. high": "178.58", "3. low": "174.13", "4. close": "177.82", "5. adjusted close": "176.290245525903", "6. volume": "2377768", "7. dividend amount": "0.0000", "8. split coefficient": "1.0"}, "2024-11-29": {"1. open": "173.93", "2. high": "176.48", "3. low": "173.42", "4. close": "176.13", "5. adjusted close": "174.614784301413", "6. volume": "1525225", "7. dividend amount": "0.0000", "8. split coefficient": "1.0"}, "2024-11-27": {"1. open": "174.38", "2. high": "175.75", "3. low": "173.67", "4. close": "174.09", "5. adjusted close": "172.592334065934", "6. volume": "1060573", "7. dividend amount": "0.0000", "8. split coefficient": "1.0"}, "2024-11-26": {"1. open": "175.21", "2. high": "175.56", "3. low": "172.29", "4. close": "173.29", "5. adjusted close": "171.799216326531", "6. volume": "1307501", "7. dividend amount": "0.0000", "8. split coefficient": "1.0"}, "2024-11-25": {"1. open": "175.5", "2. high": "177.375", "3. low": "175.27", "4. close": "175.54", "5. adjusted close": "174.029859968603", "6. volume": "2088242", "7. dividend amount": "0.0000", "8. split coefficient": "1.0"}}}