{"Symbol": "CBOE", "AssetType": "Common Stock", "Name": "Cboe Global Markets Inc", "Description": "Cboe Global Markets is an American company that owns the Chicago Board Options Exchange and the stock exchange operator BATS Global Markets.", "CIK": "1374310", "Exchange": "BATS", "Currency": "USD", "Country": "USA", "Sector": "FINANCE", "Industry": "SECURITY & COMMODITY BROKERS, DEALERS, EXCHANGES & SERVICES", "Address": "400 SOUTH LASALLE, CHICAGO, IL, US", "OfficialSite": "https://www.cboe.com", "FiscalYearEnd": "December", "LatestQuarter": "2024-12-31", "MarketCapitalization": "22695916000", "EBITDA": "1305500000", "PERatio": "29.73", "PEGRatio": "1.75", "BookValue": "40.88", "DividendPerShare": "2.36", "DividendYield": "0.0118", "EPS": "7.2", "RevenuePerShareTTM": "38.96", "ProfitMargin": "0.187", "OperatingMarginTTM": "0.272", "ReturnOnAssetsTTM": "0.0968", "ReturnOnEquityTTM": "0.185", "RevenueTTM": "4094500000", "GrossProfitTTM": "2072400000", "DilutedEPSTTM": "7.2", "QuarterlyEarningsGrowthYOY": "-0.065", "QuarterlyRevenueGrowthYOY": "0.143", "AnalystTargetPrice": "221.33", "AnalystRatingStrongBuy": "1", "AnalystRatingBuy": "3", "AnalystRatingHold": "11", "AnalystRatingSell": "1", "AnalystRatingStrongSell": "2", "TrailingPE": "29.73", "ForwardPE": "23.81", "PriceToSalesRatioTTM": "5.54", "PriceToBookRatio": "5.25", "EVToRevenue": "5.62", "EVToEBITDA": "18.15", "Beta": "0.468", "52WeekHigh": "234.37", "52WeekLow": "164.65", "50DayMovingAverage": "213.74", "200DayMovingAverage": "204.37", "SharesOutstanding": "104712000", "DividendDate": "2025-03-14", "ExDividendDate": "2025-02-28"}