{"Symbol": "UPS", "AssetType": "Common Stock", "Name": "United Parcel Service Inc", "Description": "United Parcel Service is an American multinational shipping & receiving and supply chain management company founded in 1907.", "CIK": "1090727", "Exchange": "NYSE", "Currency": "USD", "Country": "USA", "Sector": "ENERGY & TRANSPORTATION", "Industry": "TRUCKING & COURIER SERVICES (NO AIR)", "Address": "55 GLENLAKE PARKWAY NE, ATLANTA, GA, US", "OfficialSite": "https://www.ups.com", "FiscalYearEnd": "December", "LatestQuarter": "2024-12-31", "MarketCapitalization": "81727537000", "EBITDA": "11620000000", "PERatio": "14.35", "PEGRatio": "1.248", "BookValue": "19.58", "DividendPerShare": "6.52", "DividendYield": "0.0677", "EPS": "6.75", "RevenuePerShareTTM": "106.52", "ProfitMargin": "0.0635", "OperatingMarginTTM": "0.0814", "ReturnOnAssetsTTM": "0.0711", "ReturnOnEquityTTM": "0.34", "RevenueTTM": "91069997000", "GrossProfitTTM": "19359001000", "DilutedEPSTTM": "6.75", "QuarterlyEarningsGrowthYOY": "0.07", "QuarterlyRevenueGrowthYOY": "0.015", "AnalystTargetPrice": "126.16", "AnalystRatingStrongBuy": "3", "AnalystRatingBuy": "16", "AnalystRatingHold": "11", "AnalystRatingSell": "1", "AnalystRatingStrongSell": "2", "TrailingPE": "14.35", "ForwardPE": "12.29", "PriceToSalesRatioTTM": "0.897", "PriceToBookRatio": "4.909", "EVToRevenue": "1.113", "EVToEBITDA": "8.51", "Beta": "1.09", "52WeekHigh": "147.54", "52WeekLow": "90.55", "50DayMovingAverage": "110.77", "200DayMovingAverage": "125.35", "SharesOutstanding": "733687000", "DividendDate": "2025-03-06", "ExDividendDate": "2025-02-18"}