{"symbol": "PANW", "annualReports": [{"fiscalDateEnding": "2024-07-31", "reportedCurrency": "USD", "totalAssets": "19990900000", "totalCurrentAssets": "6849700000", "cashAndCashEquivalentsAtCarryingValue": "1535200000", "cashAndShortTermInvestments": "1535200000", "inventory": "1", "currentNetReceivables": "None", "totalNonCurrentAssets": "13141200000", "propertyPlantEquipment": "None", "accumulatedDepreciationAmortizationPPE": "None", "intangibleAssets": "374900000", "intangibleAssetsExcludingGoodwill": "374900000", "goodwill": "3350100000", "investments": "None", "longTermInvestments": "4173200000", "shortTermInvestments": "1043599999", "otherCurrentAssets": "926400000", "otherNonCurrentAssets": "None", "totalLiabilities": "14821200000", "totalCurrentLiabilities": "7682700000", "currentAccountsPayable": "None", "deferredRevenue": "None", "currentDebt": "None", "shortTermDebt": "1077800000", "totalNonCurrentLiabilities": "7138500000", "capitalLeaseObligations": "380500000", "longTermDebt": "None", "currentLongTermDebt": "963900000", "longTermDebtNoncurrent": "None", "shortLongTermDebtTotal": "1410300000", "otherCurrentLiabilities": "1061400000", "otherNonCurrentLiabilities": "430900000", "totalShareholderEquity": "5169700000", "treasuryStock": "None", "retainedEarnings": "1350200000", "commonStock": "3821100000", "commonStockSharesOutstanding": "708000000"}, {"fiscalDateEnding": "2023-07-31", "reportedCurrency": "USD", "totalAssets": "14501100000", "totalCurrentAssets": "6048000000", "cashAndCashEquivalentsAtCarryingValue": "1135300000", "cashAndShortTermInvestments": "1135300000", "inventory": "339200000", "currentNetReceivables": "None", "totalNonCurrentAssets": "8453100000", "propertyPlantEquipment": "354500000", "accumulatedDepreciationAmortizationPPE": "None", "intangibleAssets": "315400000", "intangibleAssetsExcludingGoodwill": "315400000", "goodwill": "2926800000", "investments": "None", "longTermInvestments": "3047900000", "shortTermInvestments": "1254700000", "otherCurrentAssets": "806000000", "otherNonCurrentAssets": "None", "totalLiabilities": "12752700000", "totalCurrentLiabilities": "7737500000", "currentAccountsPayable": "None", "deferredRevenue": "None", "currentDebt": "None", "shortTermDebt": "1991500000", "totalNonCurrentLiabilities": "5015200000", "capitalLeaseObligations": "279200000", "longTermDebt": "None", "currentLongTermDebt": "1991500000", "longTermDebtNoncurrent": "None", "shortLongTermDebtTotal": "2270700000", "otherCurrentLiabilities": "939100000", "otherNonCurrentLiabilities": "114200000", "totalShareholderEquity": "1748400000", "treasuryStock": "None", "retainedEarnings": "-1227400000", "commonStock": "3019000000", "commonStockSharesOutstanding": "684600000"}, {"fiscalDateEnding": "2022-07-31", "reportedCurrency": "USD", "totalAssets": "12253600000", "totalCurrentAssets": "6414900000", "cashAndCashEquivalentsAtCarryingValue": "2118500000", "cashAndShortTermInvestments": "2118500000", "inventory": "1", "currentNetReceivables": "None", "totalNonCurrentAssets": "5838700000", "propertyPlantEquipment": "599800000", "accumulatedDepreciationAmortizationPPE": "None", "intangibleAssets": "384500000", "intangibleAssetsExcludingGoodwill": "384500000", "goodwill": "2747700000", "investments": "None", "longTermInvestments": "1051900000", "shortTermInvestments": "1516000000", "otherCurrentAssets": "637900000", "otherNonCurrentAssets": "None", "totalLiabilities": "12043600000", "totalCurrentLiabilities": "8306300000", "currentAccountsPayable": "None", "deferredRevenue": "None", "currentDebt": "None", "shortTermDebt": "3676800001", "totalNonCurrentLiabilities": "3737300000", "capitalLeaseObligations": "276100000", "longTermDebt": "None", "currentLongTermDebt": "3676800000", "longTermDebtNoncurrent": "None", "shortLongTermDebtTotal": "3952900000", "otherCurrentLiabilities": "860299999", "otherNonCurrentLiabilities": "108400000", "totalShareholderEquity": "210000000", "treasuryStock": "None", "retainedEarnings": "-1667100000", "commonStock": "1932700000", "commonStockSharesOutstanding": "590999988"}, {"fiscalDateEnding": "2021-07-31", "reportedCurrency": "USD", "totalAssets": "10241600000", "totalCurrentAssets": "4647300000", "cashAndCashEquivalentsAtCarryingValue": "1874200000", "cashAndShortTermInvestments": "1874200000", "inventory": "None", "currentNetReceivables": "None", "totalNonCurrentAssets": "5594300000", "propertyPlantEquipment": "581300000", "accumulatedDepreciationAmortizationPPE": "None", "intangibleAssets": "498600000", "intangibleAssetsExcludingGoodwill": "498600000", "goodwill": "2710100000", "investments": "None", "longTermInvestments": "888300000", "shortTermInvestments": "1026900000", "otherCurrentAssets": "505800000", "otherNonCurrentAssets": "None", "totalLiabilities": "9478000000", "totalCurrentLiabilities": "5116700000", "currentAccountsPayable": "None", "deferredRevenue": "None", "currentDebt": "None", "shortTermDebt": "1557900000", "totalNonCurrentLiabilities": "4361300000", "capitalLeaseObligations": "313400000", "longTermDebt": "1668100000", "currentLongTermDebt": "1557900000", "longTermDebtNoncurrent": "None", "shortLongTermDebtTotal": "3539400000", "otherCurrentLiabilities": "760000000", "otherNonCurrentLiabilities": "97700000", "totalShareholderEquity": "763600000", "treasuryStock": "None", "retainedEarnings": "-1666800000", "commonStock": "2311200000", "commonStockSharesOutstanding": "578399988"}, {"fiscalDateEnding": "2020-07-31", "reportedCurrency": "USD", "totalAssets": "9065400000", "totalCurrentAssets": "5129200000", "cashAndCashEquivalentsAtCarryingValue": "2958000000", "cashAndShortTermInvestments": "2958000000", "inventory": "2", "currentNetReceivables": "None", "totalNonCurrentAssets": "3936200000", "propertyPlantEquipment": "606800000", "accumulatedDepreciationAmortizationPPE": "None", "intangibleAssets": "358200000", "intangibleAssetsExcludingGoodwill": "358200000", "goodwill": "1812900000", "investments": "None", "longTermInvestments": "554400000", "shortTermInvestments": "789800000", "otherCurrentAssets": "344300000", "otherNonCurrentAssets": "None", "totalLiabilities": "7963600000", "totalCurrentLiabilities": "2691700000", "currentAccountsPayable": "None", "deferredRevenue": "None", "currentDebt": "None", "shortTermDebt": "57900000", "totalNonCurrentLiabilities": "5271900000", "capitalLeaseObligations": "336600000", "longTermDebt": "3084100000", "currentLongTermDebt": "None", "longTermDebtNoncurrent": "None", "shortLongTermDebtTotal": "3420700000", "otherCurrentLiabilities": "521100000", "otherNonCurrentLiabilities": "90100000", "totalShareholderEquity": "1101800000", "treasuryStock": "None", "retainedEarnings": "-1167900000", "commonStock": "2259200000", "commonStockSharesOutstanding": "581399988"}, {"fiscalDateEnding": "2019-07-31", "reportedCurrency": "USD", "totalAssets": "6592200000", "totalCurrentAssets": "3664800000", "cashAndCashEquivalentsAtCarryingValue": "961400000", "cashAndShortTermInvestments": "961400000", "inventory": "None", "currentNetReceivables": "None", "totalNonCurrentAssets": "2927400000", "propertyPlantEquipment": "296000000", "accumulatedDepreciationAmortizationPPE": "None", "intangibleAssets": "280600000", "intangibleAssetsExcludingGoodwill": "280600000", "goodwill": "1352300000", "investments": "None", "longTermInvestments": "575400000", "shortTermInvestments": "1841700000", "otherCurrentAssets": "279300000", "otherNonCurrentAssets": "None", "totalLiabilities": "5005900000", "totalCurrentLiabilities": "2053300000", "currentAccountsPayable": "None", "deferredRevenue": "None", "currentDebt": "None", "shortTermDebt": "None", "totalNonCurrentLiabilities": "2952600000", "capitalLeaseObligations": "None", "longTermDebt": "1430000000", "currentLongTermDebt": "None", "longTermDebtNoncurrent": "None", "shortLongTermDebtTotal": "1430000000", "otherCurrentLiabilities": "397900000", "otherNonCurrentLiabilities": "216000000", "totalShareholderEquity": "1586300000", "treasuryStock": "None", "retainedEarnings": "-900900000", "commonStock": "2490900000", "commonStockSharesOutstanding": "566999988"}, {"fiscalDateEnding": "2018-07-31", "reportedCurrency": "USD", "totalAssets": "5823000000", "totalCurrentAssets": "4132000000", "cashAndCashEquivalentsAtCarryingValue": "2506900000", "cashAndShortTermInvestments": "2506900000", "inventory": "1", "currentNetReceivables": "None", "totalNonCurrentAssets": "1691000000", "propertyPlantEquipment": "273100000", "accumulatedDepreciationAmortizationPPE": "None", "intangibleAssets": "140800000", "intangibleAssetsExcludingGoodwill": "140800000", "goodwill": "522800000", "investments": "None", "longTermInvestments": "547500000", "shortTermInvestments": "896500000", "otherCurrentAssets": "261300000", "otherNonCurrentAssets": "None", "totalLiabilities": "4834700000", "totalCurrentLiabilities": "2139400000", "currentAccountsPayable": "None", "deferredRevenue": "None", "currentDebt": "None", "shortTermDebt": "550400000", "totalNonCurrentLiabilities": "2695300000", "capitalLeaseObligations": "None", "longTermDebt": "1369700000", "currentLongTermDebt": "550400000", "longTermDebtNoncurrent": "None", "shortLongTermDebtTotal": "1920100000", "otherCurrentLiabilities": "270700000", "otherNonCurrentLiabilities": "229600000", "totalShareholderEquity": "988300000", "treasuryStock": "0", "retainedEarnings": "-984600000", "commonStock": "1967400000", "commonStockSharesOutstanding": "550200000"}, {"fiscalDateEnding": "2017-07-31", "reportedCurrency": "USD", "totalAssets": "3438300000", "totalCurrentAssets": "1976300000", "cashAndCashEquivalentsAtCarryingValue": "744300000", "cashAndShortTermInvestments": "744300000", "inventory": "1", "currentNetReceivables": "None", "totalNonCurrentAssets": "1462000000", "propertyPlantEquipment": "211100000", "accumulatedDepreciationAmortizationPPE": "None", "intangibleAssets": "53700000", "intangibleAssetsExcludingGoodwill": "53700000", "goodwill": "238800000", "investments": "None", "longTermInvestments": "789300000", "shortTermInvestments": "630700000", "otherCurrentAssets": "169200000", "otherNonCurrentAssets": "None", "totalLiabilities": "2678700000", "totalCurrentLiabilities": "1201300000", "currentAccountsPayable": "None", "deferredRevenue": "None", "currentDebt": "None", "shortTermDebt": "524700000", "totalNonCurrentLiabilities": "1477400000", "capitalLeaseObligations": "None", "longTermDebt": "524700000", "currentLongTermDebt": "524700000", "longTermDebtNoncurrent": "None", "shortLongTermDebtTotal": "524700000", "otherCurrentLiabilities": "197400000", "otherNonCurrentLiabilities": "147600000", "totalShareholderEquity": "759600000", "treasuryStock": "0", "retainedEarnings": "-836700000", "commonStock": "1599700000", "commonStockSharesOutstanding": "543600000"}, {"fiscalDateEnding": "2016-07-31", "reportedCurrency": "USD", "totalAssets": "2761200000", "totalCurrentAssets": "1719100000", "cashAndCashEquivalentsAtCarryingValue": "734400000", "cashAndShortTermInvestments": "734400000", "inventory": "1", "currentNetReceivables": "None", "totalNonCurrentAssets": "1042100000", "propertyPlantEquipment": "117200000", "accumulatedDepreciationAmortizationPPE": "None", "intangibleAssets": "44000000", "intangibleAssetsExcludingGoodwill": "44000000", "goodwill": "163500000", "investments": "None", "longTermInvestments": "652800000", "shortTermInvestments": "551200000", "otherCurrentAssets": "84800000", "otherNonCurrentAssets": "None", "totalLiabilities": "1971300000", "totalCurrentLiabilities": "846800000", "currentAccountsPayable": "None", "deferredRevenue": "None", "currentDebt": "None", "shortTermDebt": "500200000", "totalNonCurrentLiabilities": "1124500000", "capitalLeaseObligations": "None", "longTermDebt": "508200000", "currentLongTermDebt": "500200000", "longTermDebtNoncurrent": "None", "shortLongTermDebtTotal": "1008400000", "otherCurrentLiabilities": "112700000", "otherNonCurrentLiabilities": "79400000", "totalShareholderEquity": "789900000", "treasuryStock": "0", "retainedEarnings": "-726600000", "commonStock": "1515500000", "commonStockSharesOutstanding": "522600000"}, {"fiscalDateEnding": "2015-07-31", "reportedCurrency": "USD", "totalAssets": "1965178000", "totalCurrentAssets": "1074030000", "cashAndCashEquivalentsAtCarryingValue": "375814000", "cashAndShortTermInvestments": "375814000", "inventory": "0", "currentNetReceivables": "None", "totalNonCurrentAssets": "891148000", "propertyPlantEquipment": "62878000", "accumulatedDepreciationAmortizationPPE": "None", "intangibleAssets": "52656000", "intangibleAssetsExcludingGoodwill": "52656000", "goodwill": "163522000", "investments": "None", "longTermInvestments": "538841000", "shortTermInvestments": "413165000", "otherCurrentAssets": "72685000", "otherNonCurrentAssets": "None", "totalLiabilities": "1389363000", "totalCurrentLiabilities": "1032227000", "currentAccountsPayable": "None", "deferredRevenue": "None", "currentDebt": "None", "shortTermDebt": "487084000", "totalNonCurrentLiabilities": "357136000", "capitalLeaseObligations": "None", "longTermDebt": "0", "currentLongTermDebt": "487100000", "longTermDebtNoncurrent": "None", "shortLongTermDebtTotal": "487084000", "otherCurrentLiabilities": "108086000", "otherNonCurrentLiabilities": "67335000", "totalShareholderEquity": "575815000", "treasuryStock": "0", "retainedEarnings": "-500708000", "commonStock": "8000", "commonStockSharesOutstanding": "489600000"}, {"fiscalDateEnding": "2014-07-31", "reportedCurrency": "USD", "totalAssets": "1478466000", "totalCurrentAssets": "958326000", "cashAndCashEquivalentsAtCarryingValue": "653812000", "cashAndShortTermInvestments": "653812000", "inventory": "0", "currentNetReceivables": "None", "totalNonCurrentAssets": "520140000", "propertyPlantEquipment": "48744000", "accumulatedDepreciationAmortizationPPE": "None", "intangibleAssets": "47955000", "intangibleAssetsExcludingGoodwill": "47955000", "goodwill": "155033000", "investments": "None", "longTermInvestments": "201880000", "shortTermInvestments": "118690000", "otherCurrentAssets": "50306000", "otherNonCurrentAssets": "None", "totalLiabilities": "1009883000", "totalCurrentLiabilities": "348171000", "currentAccountsPayable": "None", "deferredRevenue": "None", "currentDebt": "None", "shortTermDebt": "60937000", "totalNonCurrentLiabilities": "661712000", "capitalLeaseObligations": "None", "longTermDebt": "466875000", "currentLongTermDebt": "466875000", "longTermDebtNoncurrent": "None", "shortLongTermDebtTotal": "527812000", "otherCurrentLiabilities": "12790000", "otherNonCurrentLiabilities": "32177000", "totalShareholderEquity": "468583000", "treasuryStock": "0", "retainedEarnings": "-335726000", "commonStock": "8000", "commonStockSharesOutstanding": "445800000"}, {"fiscalDateEnding": "2013-07-31", "reportedCurrency": "USD", "totalAssets": "585606000", "totalCurrentAssets": "529699000", "cashAndCashEquivalentsAtCarryingValue": "310614000", "cashAndShortTermInvestments": "310614000", "inventory": "0", "currentNetReceivables": "None", "totalNonCurrentAssets": "55907000", "propertyPlantEquipment": "32086000", "accumulatedDepreciationAmortizationPPE": "None", "intangibleAssets": "1358000", "intangibleAssetsExcludingGoodwill": "1358000", "goodwill": "0", "investments": "None", "longTermInvestments": "17314000", "shortTermInvestments": "109007000", "otherCurrentAssets": "22617000", "otherNonCurrentAssets": "None", "totalLiabilities": "313186000", "totalCurrentLiabilities": "206102000", "currentAccountsPayable": "None", "deferredRevenue": "None", "currentDebt": "None", "shortTermDebt": "35757000", "totalNonCurrentLiabilities": "107084000", "capitalLeaseObligations": "None", "longTermDebt": "0", "currentLongTermDebt": "None", "longTermDebtNoncurrent": "None", "shortLongTermDebtTotal": "None", "otherCurrentLiabilities": "856000", "otherNonCurrentLiabilities": "11799000", "totalShareholderEquity": "272420000", "treasuryStock": "0", "retainedEarnings": "-109274000", "commonStock": "7000", "commonStockSharesOutstanding": "412092000"}, {"fiscalDateEnding": "2012-07-31", "reportedCurrency": "USD", "totalAssets": "407804000", "totalCurrentAssets": "381657000", "cashAndCashEquivalentsAtCarryingValue": "322642000", "cashAndShortTermInvestments": "322642000", "inventory": "None", "currentNetReceivables": "None", "totalNonCurrentAssets": "26147000", "propertyPlantEquipment": "20979000", "accumulatedDepreciationAmortizationPPE": "None", "intangibleAssets": "483000", "intangibleAssetsExcludingGoodwill": "483000", "goodwill": "None", "investments": "None", "longTermInvestments": "None", "shortTermInvestments": "None", "otherCurrentAssets": "13373000", "otherNonCurrentAssets": "None", "totalLiabilities": "178733000", "totalCurrentLiabilities": "122006000", "currentAccountsPayable": "None", "deferredRevenue": "None", "currentDebt": "None", "shortTermDebt": "None", "totalNonCurrentLiabilities": "56727000", "capitalLeaseObligations": "None", "longTermDebt": "None", "currentLongTermDebt": "None", "longTermDebtNoncurrent": "None", "shortLongTermDebtTotal": "None", "otherCurrentLiabilities": "26496000", "otherNonCurrentLiabilities": "None", "totalShareholderEquity": "229071000", "treasuryStock": "None", "retainedEarnings": "-80028000", "commonStock": "7000", "commonStockSharesOutstanding": "117414000"}, {"fiscalDateEnding": "2011-07-31", "reportedCurrency": "USD", "totalAssets": "91172000", "totalCurrentAssets": "76840000", "cashAndCashEquivalentsAtCarryingValue": "40517000", "cashAndShortTermInvestments": "40517000", "inventory": "4479000", "currentNetReceivables": "None", "totalNonCurrentAssets": "14332000", "propertyPlantEquipment": "12666000", "accumulatedDepreciationAmortizationPPE": "None", "intangibleAssets": "None", "intangibleAssetsExcludingGoodwill": "None", "goodwill": "None", "investments": "None", "longTermInvestments": "None", "shortTermInvestments": "None", "otherCurrentAssets": "2167000", "otherNonCurrentAssets": "None", "totalLiabilities": "162626000", "totalCurrentLiabilities": "67101000", "currentAccountsPayable": "None", "deferredRevenue": "None", "currentDebt": "None", "shortTermDebt": "13495000", "totalNonCurrentLiabilities": "95525000", "capitalLeaseObligations": "None", "longTermDebt": "None", "currentLongTermDebt": "None", "longTermDebtNoncurrent": "None", "shortLongTermDebtTotal": "None", "otherCurrentLiabilities": "2918000", "otherNonCurrentLiabilities": "None", "totalShareholderEquity": "-71454000", "treasuryStock": "None", "retainedEarnings": "-80765000", "commonStock": "2000", "commonStockSharesOutstanding": "385968000"}, {"fiscalDateEnding": "2010-07-31", "reportedCurrency": "USD", "totalAssets": "38119000", "totalCurrentAssets": "35660000", "cashAndCashEquivalentsAtCarryingValue": "18835000", "cashAndShortTermInvestments": "18835000", "inventory": "2537000", "currentNetReceivables": "None", "totalNonCurrentAssets": "2459000", "propertyPlantEquipment": "1833000", "accumulatedDepreciationAmortizationPPE": "None", "intangibleAssets": "None", "intangibleAssetsExcludingGoodwill": "None", "goodwill": "None", "investments": "None", "longTermInvestments": "None", "shortTermInvestments": "None", "otherCurrentAssets": "47000", "otherNonCurrentAssets": "None", "totalLiabilities": "103767000", "totalCurrentLiabilities": "28660000", "currentAccountsPayable": "None", "deferredRevenue": "None", "currentDebt": "None", "shortTermDebt": "7728000", "totalNonCurrentLiabilities": "75107000", "capitalLeaseObligations": "None", "longTermDebt": "None", "currentLongTermDebt": "None", "longTermDebtNoncurrent": "None", "shortLongTermDebtTotal": "None", "otherCurrentLiabilities": "1694000", "otherNonCurrentLiabilities": "None", "totalShareholderEquity": "-65648000", "treasuryStock": "None", "retainedEarnings": "-68237000", "commonStock": "2000", "commonStockSharesOutstanding": "331710000"}, {"fiscalDateEnding": "2009-07-31", "reportedCurrency": "USD", "totalAssets": "None", "totalCurrentAssets": "None", "cashAndCashEquivalentsAtCarryingValue": "None", "cashAndShortTermInvestments": "None", "inventory": "None", "currentNetReceivables": "None", "totalNonCurrentAssets": "None", "propertyPlantEquipment": "None", "accumulatedDepreciationAmortizationPPE": "None", "intangibleAssets": "None", "intangibleAssetsExcludingGoodwill": "None", "goodwill": "None", "investments": "None", "longTermInvestments": "None", "shortTermInvestments": "None", "otherCurrentAssets": "None", "otherNonCurrentAssets": "None", "totalLiabilities": "None", "totalCurrentLiabilities": "None", "currentAccountsPayable": "None", "deferredRevenue": "None", "currentDebt": "None", "shortTermDebt": "None", "totalNonCurrentLiabilities": "None", "capitalLeaseObligations": "None", "longTermDebt": "None", "currentLongTermDebt": "None", "longTermDebtNoncurrent": "None", "shortLongTermDebtTotal": "None", "otherCurrentLiabilities": "None", "otherNonCurrentLiabilities": "None", "totalShareholderEquity": "None", "treasuryStock": "None", "retainedEarnings": "None", "commonStock": "None", "commonStockSharesOutstanding": "331710000"}], "quarterlyReports": [{"fiscalDateEnding": "2025-01-31", "reportedCurrency": "USD", "totalAssets": "20951700000", "totalCurrentAssets": "6339800000", "cashAndCashEquivalentsAtCarryingValue": "2226300000", "cashAndShortTermInvestments": "2226300000", "inventory": "None", "currentNetReceivables": "None", "totalNonCurrentAssets": "14611900000", "propertyPlantEquipment": "None", "accumulatedDepreciationAmortizationPPE": "None", "intangibleAssets": "771400000", "intangibleAssetsExcludingGoodwill": "771400000", "goodwill": "4050800000", "investments": "None", "longTermInvestments": "4559800000", "shortTermInvestments": "1006600000", "otherCurrentAssets": "856500000", "otherNonCurrentAssets": "None", "totalLiabilities": "14576400000", "totalCurrentLiabilities": "7552200000", "currentAccountsPayable": "None", "deferredRevenue": "None", "currentDebt": "None", "shortTermDebt": "None", "totalNonCurrentLiabilities": "7024200000", "capitalLeaseObligations": "363000000", "longTermDebt": "None", "currentLongTermDebt": "533800000", "longTermDebtNoncurrent": "None", "shortLongTermDebtTotal": "896800000", "otherCurrentLiabilities": "1803000000", "otherNonCurrentLiabilities": "882600000", "totalShareholderEquity": "6375300000", "treasuryStock": "None", "retainedEarnings": "1968200000", "commonStock": "4421000000", "commonStockSharesOutstanding": "709000000"}, {"fiscalDateEnding": "2024-10-31", "reportedCurrency": "USD", "totalAssets": "20374600000", "totalCurrentAssets": "6242700000", "cashAndCashEquivalentsAtCarryingValue": "2282800000", "cashAndShortTermInvestments": "2282800000", "inventory": "None", "currentNetReceivables": "None", "totalNonCurrentAssets": "14131900000", "propertyPlantEquipment": "None", "accumulatedDepreciationAmortizationPPE": "None", "intangibleAssets": "809600000", "intangibleAssetsExcludingGoodwill": "809600000", "goodwill": "4050800000", "investments": "None", "longTermInvestments": "4119700000", "shortTermInvestments": "1108200000", "otherCurrentAssets": "913700000", "otherNonCurrentAssets": "None", "totalLiabilities": "14462800000", "totalCurrentLiabilities": "7402700000", "currentAccountsPayable": "None", "deferredRevenue": "None", "currentDebt": "None", "shortTermDebt": "None", "totalNonCurrentLiabilities": "7060100000", "capitalLeaseObligations": "379600000", "longTermDebt": "None", "currentLongTermDebt": "645800000", "longTermDebtNoncurrent": "None", "shortLongTermDebtTotal": "1025400000", "otherCurrentLiabilities": "1683400000", "otherNonCurrentLiabilities": "843800000", "totalShareholderEquity": "5911800000", "treasuryStock": "None", "retainedEarnings": "1700900000", "commonStock": "4214900000", "commonStockSharesOutstanding": "709000000"}, {"fiscalDateEnding": "2024-07-31", "reportedCurrency": "USD", "totalAssets": "19990900000", "totalCurrentAssets": "6849700000", "cashAndCashEquivalentsAtCarryingValue": "1535200000", "cashAndShortTermInvestments": "1535200000", "inventory": "1", "currentNetReceivables": "None", "totalNonCurrentAssets": "13141200000", "propertyPlantEquipment": "None", "accumulatedDepreciationAmortizationPPE": "None", "intangibleAssets": "374900000", "intangibleAssetsExcludingGoodwill": "374900000", "goodwill": "3350100000", "investments": "None", "longTermInvestments": "4173200000", "shortTermInvestments": "1043599999", "otherCurrentAssets": "926400000", "otherNonCurrentAssets": "None", "totalLiabilities": "14821200000", "totalCurrentLiabilities": "7682700000", "currentAccountsPayable": "None", "deferredRevenue": "None", "currentDebt": "None", "shortTermDebt": "1029800000", "totalNonCurrentLiabilities": "7138500000", "capitalLeaseObligations": "380500000", "longTermDebt": "None", "currentLongTermDebt": "963900000", "longTermDebtNoncurrent": "None", "shortLongTermDebtTotal": "1410300000", "otherCurrentLiabilities": "1061400000", "otherNonCurrentLiabilities": "430900000", "totalShareholderEquity": "5169700000", "treasuryStock": "None", "retainedEarnings": "1350200000", "commonStock": "3821100000", "commonStockSharesOutstanding": "707800000"}, {"fiscalDateEnding": "2024-04-30", "reportedCurrency": "USD", "totalAssets": "17930800000", "totalCurrentAssets": "5581800000", "cashAndCashEquivalentsAtCarryingValue": "1381900000", "cashAndShortTermInvestments": "1381900000", "inventory": "None", "currentNetReceivables": "None", "totalNonCurrentAssets": "12349000000", "propertyPlantEquipment": "None", "accumulatedDepreciationAmortizationPPE": "None", "intangibleAssets": "407600000", "intangibleAssetsExcludingGoodwill": "407600000", "goodwill": "3372700000", "investments": "None", "longTermInvestments": "3504400000", "shortTermInvestments": "1516700000", "otherCurrentAssets": "740700000", "otherNonCurrentAssets": "None", "totalLiabilities": "13463000000", "totalCurrentLiabilities": "7084800000", "currentAccountsPayable": "None", "deferredRevenue": "None", "currentDebt": "None", "shortTermDebt": "1162500000", "totalNonCurrentLiabilities": "6378200000", "capitalLeaseObligations": "369800000", "longTermDebt": "None", "currentLongTermDebt": "1162500000", "longTermDebtNoncurrent": "None", "shortLongTermDebtTotal": "1532300000", "otherCurrentLiabilities": "798500000", "otherNonCurrentLiabilities": "352700000", "totalShareholderEquity": "4467800000", "treasuryStock": "None", "retainedEarnings": "992500000", "commonStock": "3530700000", "commonStockSharesOutstanding": "709200000"}, {"fiscalDateEnding": "2024-01-31", "reportedCurrency": "USD", "totalAssets": "18292000000", "totalCurrentAssets": "6118700000", "cashAndCashEquivalentsAtCarryingValue": "1782500000", "cashAndShortTermInvestments": "1782500000", "inventory": "1", "currentNetReceivables": "None", "totalNonCurrentAssets": "12173300000", "propertyPlantEquipment": "None", "accumulatedDepreciationAmortizationPPE": "None", "intangibleAssets": "440100000", "intangibleAssetsExcludingGoodwill": "440100000", "goodwill": "3372700000", "investments": "None", "longTermInvestments": "3619600000", "shortTermInvestments": "1588500000", "otherCurrentAssets": "733900000", "otherNonCurrentAssets": "None", "totalLiabilities": "13934800000", "totalCurrentLiabilities": "7765500000", "currentAccountsPayable": "None", "deferredRevenue": "None", "currentDebt": "None", "shortTermDebt": "1821800000", "totalNonCurrentLiabilities": "6169299999", "capitalLeaseObligations": "362700000", "longTermDebt": "None", "currentLongTermDebt": "1821800000", "longTermDebtNoncurrent": "None", "shortLongTermDebtTotal": "2184500000", "otherCurrentLiabilities": "846800000", "otherNonCurrentLiabilities": "317800000", "totalShareholderEquity": "4357200000", "treasuryStock": "None", "retainedEarnings": "713700000", "commonStock": "3650000000", "commonStockSharesOutstanding": "715000000"}, {"fiscalDateEnding": "2023-10-31", "reportedCurrency": "USD", "totalAssets": "14808500000", "totalCurrentAssets": "6477600000", "cashAndCashEquivalentsAtCarryingValue": "2491400000", "cashAndShortTermInvestments": "2491400000", "inventory": "328700000", "currentNetReceivables": "None", "totalNonCurrentAssets": "8330900000", "propertyPlantEquipment": "None", "accumulatedDepreciationAmortizationPPE": "None", "intangibleAssets": "290500000", "intangibleAssetsExcludingGoodwill": "290500000", "goodwill": "2926800000", "investments": "None", "longTermInvestments": "2988900000", "shortTermInvestments": "1402400000", "otherCurrentAssets": "396200000", "otherNonCurrentAssets": "None", "totalLiabilities": "12638000000", "totalCurrentLiabilities": "7513400000", "currentAccountsPayable": "None", "deferredRevenue": "None", "currentDebt": "None", "shortTermDebt": "1946700000", "totalNonCurrentLiabilities": "5124600000", "capitalLeaseObligations": "275800000", "longTermDebt": "None", "currentLongTermDebt": "1946700000", "longTermDebtNoncurrent": "None", "shortLongTermDebtTotal": "2222500000", "otherCurrentLiabilities": "702900000", "otherNonCurrentLiabilities": "138000000", "totalShareholderEquity": "2170500000", "treasuryStock": "None", "retainedEarnings": "-1033200000", "commonStock": "3296700000", "commonStockSharesOutstanding": "699600000"}, {"fiscalDateEnding": "2023-07-31", "reportedCurrency": "USD", "totalAssets": "14501100000", "totalCurrentAssets": "6048000000", "cashAndCashEquivalentsAtCarryingValue": "1135300000", "cashAndShortTermInvestments": "1135300000", "inventory": "339200000", "currentNetReceivables": "None", "totalNonCurrentAssets": "8453100000", "propertyPlantEquipment": "354500000", "accumulatedDepreciationAmortizationPPE": "None", "intangibleAssets": "315400000", "intangibleAssetsExcludingGoodwill": "315400000", "goodwill": "2926800000", "investments": "None", "longTermInvestments": "3047900000", "shortTermInvestments": "1254700000", "otherCurrentAssets": "466800000", "otherNonCurrentAssets": "None", "totalLiabilities": "12752700000", "totalCurrentLiabilities": "7737500000", "currentAccountsPayable": "None", "deferredRevenue": "None", "currentDebt": "None", "shortTermDebt": "1991500000", "totalNonCurrentLiabilities": "5015200000", "capitalLeaseObligations": "279200000", "longTermDebt": "None", "currentLongTermDebt": "1991500000", "longTermDebtNoncurrent": "None", "shortLongTermDebtTotal": "2270700000", "otherCurrentLiabilities": "939100000", "otherNonCurrentLiabilities": "114200000", "totalShareholderEquity": "1748400000", "treasuryStock": "None", "retainedEarnings": "-1227400000", "commonStock": "3019000000", "commonStockSharesOutstanding": "709000000"}, {"fiscalDateEnding": "2023-04-30", "reportedCurrency": "USD", "totalAssets": "14170500000", "totalCurrentAssets": "6413600000", "cashAndCashEquivalentsAtCarryingValue": "1992900000", "cashAndShortTermInvestments": "1992900000", "inventory": "317300000", "currentNetReceivables": "None", "totalNonCurrentAssets": "7756900000", "propertyPlantEquipment": "341700000", "accumulatedDepreciationAmortizationPPE": "None", "intangibleAssets": "340600000", "intangibleAssetsExcludingGoodwill": "340600000", "goodwill": "2926800000", "investments": "None", "longTermInvestments": "2709800000", "shortTermInvestments": "1965300000", "otherCurrentAssets": "694500000", "otherNonCurrentAssets": "None", "totalLiabilities": "12938100000", "totalCurrentLiabilities": "8641200000", "currentAccountsPayable": "None", "deferredRevenue": "None", "currentDebt": "None", "shortTermDebt": "3682100000", "totalNonCurrentLiabilities": "4296900000", "capitalLeaseObligations": "264500000", "longTermDebt": "None", "currentLongTermDebt": "3682100000", "longTermDebtNoncurrent": "None", "shortLongTermDebtTotal": "3946600000", "otherCurrentLiabilities": "720800000", "otherNonCurrentLiabilities": "4296900000", "totalShareholderEquity": "1232400000", "treasuryStock": "None", "retainedEarnings": "-1455100000", "commonStock": "2708200000", "commonStockSharesOutstanding": "689400000"}, {"fiscalDateEnding": "2023-01-31", "reportedCurrency": "USD", "totalAssets": "13163400000", "totalCurrentAssets": "5405800000", "cashAndCashEquivalentsAtCarryingValue": "1346300000", "cashAndShortTermInvestments": "1346300000", "inventory": "313400000", "currentNetReceivables": "None", "totalNonCurrentAssets": "7757600000", "propertyPlantEquipment": "344700000", "accumulatedDepreciationAmortizationPPE": "None", "intangibleAssets": "361700000", "intangibleAssetsExcludingGoodwill": "361700000", "goodwill": "2912300000", "investments": "None", "longTermInvestments": "2820600000", "shortTermInvestments": "2000600000", "otherCurrentAssets": "467400000", "otherNonCurrentAssets": "None", "totalLiabilities": "12434400000", "totalCurrentLiabilities": "8475100000", "currentAccountsPayable": "None", "deferredRevenue": "None", "currentDebt": "None", "shortTermDebt": "3680300000", "totalNonCurrentLiabilities": "3959300000", "capitalLeaseObligations": "274200000", "longTermDebt": "None", "currentLongTermDebt": "3680300000", "longTermDebtNoncurrent": "None", "shortLongTermDebtTotal": "3954500000", "otherCurrentLiabilities": "724000000", "otherNonCurrentLiabilities": "3959300000", "totalShareholderEquity": "729000000", "treasuryStock": "None", "retainedEarnings": "-1562900000", "commonStock": "2303000000", "commonStockSharesOutstanding": "663200000"}, {"fiscalDateEnding": "2022-10-31", "reportedCurrency": "USD", "totalAssets": "12543800000", "totalCurrentAssets": "5733500000", "cashAndCashEquivalentsAtCarryingValue": "2067200000", "cashAndShortTermInvestments": "2067200000", "inventory": "381100000", "currentNetReceivables": "None", "totalNonCurrentAssets": "6810300000", "propertyPlantEquipment": "614100000", "accumulatedDepreciationAmortizationPPE": "None", "intangibleAssets": "355400000", "intangibleAssetsExcludingGoodwill": "355400000", "goodwill": "2747700000", "investments": "None", "longTermInvestments": "2094700000", "shortTermInvestments": "1736500000", "otherCurrentAssets": "691700000", "otherNonCurrentAssets": "None", "totalLiabilities": "12035800000", "totalCurrentLiabilities": "8195100000", "currentAccountsPayable": "None", "deferredRevenue": "None", "currentDebt": "None", "shortTermDebt": "3678600000", "totalNonCurrentLiabilities": "3840700000", "capitalLeaseObligations": "283100000", "longTermDebt": "None", "currentLongTermDebt": "3678600000", "longTermDebtNoncurrent": "None", "shortLongTermDebtTotal": "3961700000", "otherCurrentLiabilities": "649300000", "otherNonCurrentLiabilities": "119300000", "totalShareholderEquity": "508000000", "treasuryStock": "None", "retainedEarnings": "-1647100000", "commonStock": "2266200000", "commonStockSharesOutstanding": "676800000"}, {"fiscalDateEnding": "2022-07-31", "reportedCurrency": "USD", "totalAssets": "12253600000", "totalCurrentAssets": "6414900000", "cashAndCashEquivalentsAtCarryingValue": "2118500000", "cashAndShortTermInvestments": "2118500000", "inventory": "1", "currentNetReceivables": "None", "totalNonCurrentAssets": "5838700000", "propertyPlantEquipment": "599800000", "accumulatedDepreciationAmortizationPPE": "None", "intangibleAssets": "384500000", "intangibleAssetsExcludingGoodwill": "384500000", "goodwill": "2747700000", "investments": "None", "longTermInvestments": "1051900000", "shortTermInvestments": "1516000000", "otherCurrentAssets": "637900000", "otherNonCurrentAssets": "None", "totalLiabilities": "12043600000", "totalCurrentLiabilities": "8306300000", "currentAccountsPayable": "None", "deferredRevenue": "None", "currentDebt": "None", "shortTermDebt": "3676800000", "totalNonCurrentLiabilities": "3737300000", "capitalLeaseObligations": "276100000", "longTermDebt": "None", "currentLongTermDebt": "3676800000", "longTermDebtNoncurrent": "None", "shortLongTermDebtTotal": "3952900000", "otherCurrentLiabilities": "860300000", "otherNonCurrentLiabilities": "108400000", "totalShareholderEquity": "210000000", "treasuryStock": "None", "retainedEarnings": "-1667100000", "commonStock": "1932700000", "commonStockSharesOutstanding": "672600000"}, {"fiscalDateEnding": "2022-04-30", "reportedCurrency": "USD", "totalAssets": "11100000000", "totalCurrentAssets": "5697600000", "cashAndCashEquivalentsAtCarryingValue": "2419900000", "cashAndShortTermInvestments": "2419900000", "inventory": "None", "currentNetReceivables": "None", "totalNonCurrentAssets": "5402400000", "propertyPlantEquipment": "355600000", "accumulatedDepreciationAmortizationPPE": "None", "intangibleAssets": "412100000", "intangibleAssetsExcludingGoodwill": "412100000", "goodwill": "2731300000", "investments": "None", "longTermInvestments": "714700000", "shortTermInvestments": "1454700000", "otherCurrentAssets": "582400000", "otherNonCurrentAssets": "None", "totalLiabilities": "10762400000", "totalCurrentLiabilities": "7677200000", "currentAccountsPayable": "None", "deferredRevenue": "None", "currentDebt": "None", "shortTermDebt": "3675700000", "totalNonCurrentLiabilities": "3085200000", "capitalLeaseObligations": "275700000", "longTermDebt": "None", "currentLongTermDebt": "3675700000", "longTermDebtNoncurrent": "None", "shortLongTermDebtTotal": "3951400000", "otherCurrentLiabilities": "740600000", "otherNonCurrentLiabilities": "103000000", "totalShareholderEquity": "337600000", "treasuryStock": "None", "retainedEarnings": "-1670400000", "commonStock": "2066300000", "commonStockSharesOutstanding": "593400000"}, {"fiscalDateEnding": "2022-01-31", "reportedCurrency": "USD", "totalAssets": "10400500000", "totalCurrentAssets": "4868600000", "cashAndCashEquivalentsAtCarryingValue": "1922700000", "cashAndShortTermInvestments": "1922700000", "inventory": "None", "currentNetReceivables": "None", "totalNonCurrentAssets": "5531900000", "propertyPlantEquipment": "601500000", "accumulatedDepreciationAmortizationPPE": "None", "intangibleAssets": "443900000", "intangibleAssetsExcludingGoodwill": "443900000", "goodwill": "2731300000", "investments": "None", "longTermInvestments": "851000000", "shortTermInvestments": "1417600000", "otherCurrentAssets": "576100000", "otherNonCurrentAssets": "None", "totalLiabilities": "10282700000", "totalCurrentLiabilities": "7406400000", "currentAccountsPayable": "None", "deferredRevenue": "None", "currentDebt": "None", "shortTermDebt": "3673900000", "totalNonCurrentLiabilities": "2876300000", "capitalLeaseObligations": "282400000", "longTermDebt": "None", "currentLongTermDebt": "3673900000", "longTermDebtNoncurrent": "None", "shortLongTermDebtTotal": "3956300000", "otherCurrentLiabilities": "653900000", "otherNonCurrentLiabilities": "102900000", "totalShareholderEquity": "117800000", "treasuryStock": "None", "retainedEarnings": "-1597200000", "commonStock": "1745200000", "commonStockSharesOutstanding": "589000000"}, {"fiscalDateEnding": "2021-10-31", "reportedCurrency": "USD", "totalAssets": "10426400000", "totalCurrentAssets": "4839100000", "cashAndCashEquivalentsAtCarryingValue": "2272900000", "cashAndShortTermInvestments": "2272900000", "inventory": "None", "currentNetReceivables": "None", "totalNonCurrentAssets": "5587300000", "propertyPlantEquipment": "324300000", "accumulatedDepreciationAmortizationPPE": "None", "intangibleAssets": "471300000", "intangibleAssetsExcludingGoodwill": "471300000", "goodwill": "2732300000", "investments": "None", "longTermInvestments": "898800000", "shortTermInvestments": "1188500000", "otherCurrentAssets": "565600000", "otherNonCurrentAssets": "None", "totalLiabilities": "9907500000", "totalCurrentLiabilities": "7144400000", "currentAccountsPayable": "None", "deferredRevenue": "None", "currentDebt": "None", "shortTermDebt": "3672100000", "totalNonCurrentLiabilities": "2763100000", "capitalLeaseObligations": "299500000", "longTermDebt": "None", "currentLongTermDebt": "3672100000", "longTermDebtNoncurrent": "None", "shortLongTermDebtTotal": "3971600000", "otherCurrentLiabilities": "575400000", "otherNonCurrentLiabilities": "107000000", "totalShareholderEquity": "518900000", "treasuryStock": "None", "retainedEarnings": "-1503700000", "commonStock": "2033900000", "commonStockSharesOutstanding": "585800000"}, {"fiscalDateEnding": "2021-07-31", "reportedCurrency": "USD", "totalAssets": "10241600000", "totalCurrentAssets": "4647300000", "cashAndCashEquivalentsAtCarryingValue": "1874200000", "cashAndShortTermInvestments": "1874200000", "inventory": "None", "currentNetReceivables": "None", "totalNonCurrentAssets": "5594300000", "propertyPlantEquipment": "581300000", "accumulatedDepreciationAmortizationPPE": "None", "intangibleAssets": "498600000", "intangibleAssetsExcludingGoodwill": "498600000", "goodwill": "2710100000", "investments": "None", "longTermInvestments": "888300000", "shortTermInvestments": "1026900000", "otherCurrentAssets": "505800000", "otherNonCurrentAssets": "None", "totalLiabilities": "9478000000", "totalCurrentLiabilities": "5116700000", "currentAccountsPayable": "None", "deferredRevenue": "None", "currentDebt": "None", "shortTermDebt": "1557900000", "totalNonCurrentLiabilities": "4361300000", "capitalLeaseObligations": "313400000", "longTermDebt": "1668100000", "currentLongTermDebt": "1557900000", "longTermDebtNoncurrent": "None", "shortLongTermDebtTotal": "3539400000", "otherCurrentLiabilities": "760000000", "otherNonCurrentLiabilities": "97700000", "totalShareholderEquity": "763600000", "treasuryStock": "None", "retainedEarnings": "-1666800000", "commonStock": "2311200000", "commonStockSharesOutstanding": "583200000"}, {"fiscalDateEnding": "2021-04-30", "reportedCurrency": "USD", "totalAssets": "9562100000", "totalCurrentAssets": "4140900000", "cashAndCashEquivalentsAtCarryingValue": "1886100000", "cashAndShortTermInvestments": "1886100000", "inventory": "None", "currentNetReceivables": "None", "totalNonCurrentAssets": "5421200000", "propertyPlantEquipment": "322700000", "accumulatedDepreciationAmortizationPPE": "None", "intangibleAssets": "530300000", "intangibleAssetsExcludingGoodwill": "530300000", "goodwill": "2713100000", "investments": "None", "longTermInvestments": "885400000", "shortTermInvestments": "1059300000", "otherCurrentAssets": "428700000", "otherNonCurrentAssets": "None", "totalLiabilities": "8564900000", "totalCurrentLiabilities": "3007300000", "currentAccountsPayable": "None", "deferredRevenue": "None", "currentDebt": "None", "shortTermDebt": "317000000", "totalNonCurrentLiabilities": "5557600000", "capitalLeaseObligations": "317700000", "longTermDebt": "3190600000", "currentLongTermDebt": "None", "longTermDebtNoncurrent": "None", "shortLongTermDebtTotal": "3508300000", "otherCurrentLiabilities": "514300000", "otherNonCurrentLiabilities": "95500000", "totalShareholderEquity": "997200000", "treasuryStock": "None", "retainedEarnings": "-1547500000", "commonStock": "2541100000", "commonStockSharesOutstanding": "581400000"}, {"fiscalDateEnding": "2021-01-31", "reportedCurrency": "USD", "totalAssets": "9488400000", "totalCurrentAssets": "4275800000", "cashAndCashEquivalentsAtCarryingValue": "2113200000", "cashAndShortTermInvestments": "2113200000", "inventory": "None", "currentNetReceivables": "None", "totalNonCurrentAssets": "5212600000", "propertyPlantEquipment": "330700000", "accumulatedDepreciationAmortizationPPE": "None", "intangibleAssets": "541100000", "intangibleAssetsExcludingGoodwill": "541100000", "goodwill": "2583500000", "investments": "None", "longTermInvestments": "857100000", "shortTermInvestments": "1058000000", "otherCurrentAssets": "435400000", "otherNonCurrentAssets": "None", "totalLiabilities": "8289900000", "totalCurrentLiabilities": "4376300000", "currentAccountsPayable": "None", "deferredRevenue": "None", "currentDebt": "None", "shortTermDebt": "1525600000", "totalNonCurrentLiabilities": "3913600000", "capitalLeaseObligations": "317900000", "longTermDebt": "1629100000", "currentLongTermDebt": "1525600000", "longTermDebtNoncurrent": "None", "shortLongTermDebtTotal": "3472600000", "otherCurrentLiabilities": "516300000", "otherNonCurrentLiabilities": "93900000", "totalShareholderEquity": "1198500000", "treasuryStock": "None", "retainedEarnings": "-1402400000", "commonStock": "2429800000", "commonStockSharesOutstanding": "575400000"}, {"fiscalDateEnding": "2020-10-31", "reportedCurrency": "USD", "totalAssets": "8726500000", "totalCurrentAssets": "4300900000", "cashAndCashEquivalentsAtCarryingValue": "2142000000", "cashAndShortTermInvestments": "2142000000", "inventory": "1", "currentNetReceivables": "None", "totalNonCurrentAssets": "4425600000", "propertyPlantEquipment": "337900000", "accumulatedDepreciationAmortizationPPE": "None", "intangibleAssets": "388800000", "intangibleAssetsExcludingGoodwill": "388800000", "goodwill": "1968600000", "investments": "None", "longTermInvestments": "873200000", "shortTermInvestments": "1075600000", "otherCurrentAssets": "407800000", "otherNonCurrentAssets": "None", "totalLiabilities": "7979500000", "totalCurrentLiabilities": "2635100000", "currentAccountsPayable": "None", "deferredRevenue": "None", "currentDebt": "None", "shortTermDebt": "None", "totalNonCurrentLiabilities": "5344400000", "capitalLeaseObligations": "323900000", "longTermDebt": "3119200000", "currentLongTermDebt": "None", "longTermDebtNoncurrent": "None", "shortLongTermDebtTotal": "3443100000", "otherCurrentLiabilities": "449100000", "otherNonCurrentLiabilities": "92000000", "totalShareholderEquity": "747000000", "treasuryStock": "None", "retainedEarnings": "-1260100000", "commonStock": "2003900000", "commonStockSharesOutstanding": "573000000"}, {"fiscalDateEnding": "2020-07-31", "reportedCurrency": "USD", "totalAssets": "9065400000", "totalCurrentAssets": "5129200000", "cashAndCashEquivalentsAtCarryingValue": "2958000000", "cashAndShortTermInvestments": "2958000000", "inventory": "2", "currentNetReceivables": "None", "totalNonCurrentAssets": "3936200000", "propertyPlantEquipment": "606800000", "accumulatedDepreciationAmortizationPPE": "None", "intangibleAssets": "358200000", "intangibleAssetsExcludingGoodwill": "358200000", "goodwill": "1812900000", "investments": "None", "longTermInvestments": "554400000", "shortTermInvestments": "789800000", "otherCurrentAssets": "344300000", "otherNonCurrentAssets": "None", "totalLiabilities": "7963600000", "totalCurrentLiabilities": "2691700000", "currentAccountsPayable": "None", "deferredRevenue": "None", "currentDebt": "None", "shortTermDebt": "None", "totalNonCurrentLiabilities": "5271900000", "capitalLeaseObligations": "336600000", "longTermDebt": "3084100000", "currentLongTermDebt": "None", "longTermDebtNoncurrent": "None", "shortLongTermDebtTotal": "3420700000", "otherCurrentLiabilities": "579000000", "otherNonCurrentLiabilities": "90100000", "totalShareholderEquity": "1101800000", "treasuryStock": "None", "retainedEarnings": "-1167900000", "commonStock": "2259200000", "commonStockSharesOutstanding": "576000000"}, {"fiscalDateEnding": "2020-04-30", "reportedCurrency": "USD", "totalAssets": "6501800000", "totalCurrentAssets": "3014000000", "cashAndCashEquivalentsAtCarryingValue": "1484700000", "cashAndShortTermInvestments": "1484700000", "inventory": "None", "currentNetReceivables": "None", "totalNonCurrentAssets": "3487800000", "propertyPlantEquipment": "357200000", "accumulatedDepreciationAmortizationPPE": "None", "intangibleAssets": "380600000", "intangibleAssetsExcludingGoodwill": "380600000", "goodwill": "1812900000", "investments": "None", "longTermInvestments": "151200000", "shortTermInvestments": "554100000", "otherCurrentAssets": "306400000", "otherNonCurrentAssets": "None", "totalLiabilities": "5757100000", "totalCurrentLiabilities": "2335700000", "currentAccountsPayable": "None", "deferredRevenue": "None", "currentDebt": "None", "shortTermDebt": "57300000", "totalNonCurrentLiabilities": "3421400000", "capitalLeaseObligations": "344600000", "longTermDebt": "1477000000", "currentLongTermDebt": "None", "longTermDebtNoncurrent": "None", "shortLongTermDebtTotal": "1821600000", "otherCurrentLiabilities": "428800000", "otherNonCurrentLiabilities": "83800000", "totalShareholderEquity": "744700000", "treasuryStock": "None", "retainedEarnings": "-1109000000", "commonStock": "1855700000", "commonStockSharesOutstanding": "580200000"}, {"fiscalDateEnding": "2020-01-31", "reportedCurrency": "USD", "totalAssets": "7184100000", "totalCurrentAssets": "3978200000", "cashAndCashEquivalentsAtCarryingValue": "2000000000", "cashAndShortTermInvestments": "2000000000", "inventory": "1", "currentNetReceivables": "None", "totalNonCurrentAssets": "3205900000", "propertyPlantEquipment": "311400000", "accumulatedDepreciationAmortizationPPE": "None", "intangibleAssets": "290000000", "intangibleAssetsExcludingGoodwill": "290000000", "goodwill": "1511700000", "investments": "None", "longTermInvestments": "317900000", "shortTermInvestments": "1133900000", "otherCurrentAssets": "304000000", "otherNonCurrentAssets": "None", "totalLiabilities": "5575600000", "totalCurrentLiabilities": "2239500000", "currentAccountsPayable": "None", "deferredRevenue": "None", "currentDebt": "None", "shortTermDebt": "None", "totalNonCurrentLiabilities": "3336100000", "capitalLeaseObligations": "353500000", "longTermDebt": "1461200000", "currentLongTermDebt": "None", "longTermDebtNoncurrent": "None", "shortLongTermDebtTotal": "1814700000", "otherCurrentLiabilities": "426400000", "otherNonCurrentLiabilities": "80600000", "totalShareholderEquity": "1608500000", "treasuryStock": "None", "retainedEarnings": "-1034200000", "commonStock": "2644500000", "commonStockSharesOutstanding": "589800000"}, {"fiscalDateEnding": "2019-10-31", "reportedCurrency": "USD", "totalAssets": "6824800000", "totalCurrentAssets": "3649800000", "cashAndCashEquivalentsAtCarryingValue": "1263700000", "cashAndShortTermInvestments": "1263700000", "inventory": "None", "currentNetReceivables": "None", "totalNonCurrentAssets": "3175000000", "propertyPlantEquipment": "599000000", "accumulatedDepreciationAmortizationPPE": "None", "intangibleAssets": "284100000", "intangibleAssetsExcludingGoodwill": "284100000", "goodwill": "1400400000", "investments": "None", "longTermInvestments": "467600000", "shortTermInvestments": "1597500000", "otherCurrentAssets": "289400000", "otherNonCurrentAssets": "None", "totalLiabilities": "5308400000", "totalCurrentLiabilities": "2051600000", "currentAccountsPayable": "None", "deferredRevenue": "None", "currentDebt": "None", "shortTermDebt": "61800000", "totalNonCurrentLiabilities": "3256800000", "capitalLeaseObligations": "371600000", "longTermDebt": "1445500000", "currentLongTermDebt": "None", "longTermDebtNoncurrent": "None", "shortLongTermDebtTotal": "1817100000", "otherCurrentLiabilities": "318000000", "otherNonCurrentLiabilities": "82600000", "totalShareholderEquity": "1516400000", "treasuryStock": "None", "retainedEarnings": "-960500000", "commonStock": "2477500000", "commonStockSharesOutstanding": "579600000"}, {"fiscalDateEnding": "2019-07-31", "reportedCurrency": "USD", "totalAssets": "6592200000", "totalCurrentAssets": "3664800000", "cashAndCashEquivalentsAtCarryingValue": "961400000", "cashAndShortTermInvestments": "961400000", "inventory": "None", "currentNetReceivables": "None", "totalNonCurrentAssets": "2927400000", "propertyPlantEquipment": "296000000", "accumulatedDepreciationAmortizationPPE": "None", "intangibleAssets": "280600000", "intangibleAssetsExcludingGoodwill": "280600000", "goodwill": "1352300000", "investments": "None", "longTermInvestments": "575400000", "shortTermInvestments": "1841700000", "otherCurrentAssets": "279300000", "otherNonCurrentAssets": "None", "totalLiabilities": "5005900000", "totalCurrentLiabilities": "2053300000", "currentAccountsPayable": "None", "deferredRevenue": "None", "currentDebt": "None", "shortTermDebt": "None", "totalNonCurrentLiabilities": "2952600000", "capitalLeaseObligations": "None", "longTermDebt": "1430000000", "currentLongTermDebt": "None", "longTermDebtNoncurrent": "None", "shortLongTermDebtTotal": "1430000000", "otherCurrentLiabilities": "397900000", "otherNonCurrentLiabilities": "216000000", "totalShareholderEquity": "1586300000", "treasuryStock": "None", "retainedEarnings": "-900900000", "commonStock": "2490900000", "commonStockSharesOutstanding": "574800000"}, {"fiscalDateEnding": "2019-04-30", "reportedCurrency": "USD", "totalAssets": "6261800000", "totalCurrentAssets": "3717500000", "cashAndCashEquivalentsAtCarryingValue": "1314900000", "cashAndShortTermInvestments": "1314900000", "inventory": "1", "currentNetReceivables": "None", "totalNonCurrentAssets": "2544300000", "propertyPlantEquipment": "275000000", "accumulatedDepreciationAmortizationPPE": "None", "intangibleAssets": "234200000", "intangibleAssetsExcludingGoodwill": "234200000", "goodwill": "1027300000", "investments": "None", "longTermInvestments": "669900000", "shortTermInvestments": "1733200000", "otherCurrentAssets": "261900000", "otherNonCurrentAssets": "None", "totalLiabilities": "4807200000", "totalCurrentLiabilities": "1998800000", "currentAccountsPayable": "None", "deferredRevenue": "None", "currentDebt": "None", "shortTermDebt": "158100000", "totalNonCurrentLiabilities": "2808400000", "capitalLeaseObligations": "None", "longTermDebt": "1414700000", "currentLongTermDebt": "158100000", "longTermDebtNoncurrent": "None", "shortLongTermDebtTotal": "1572800000", "otherCurrentLiabilities": "322500000", "otherNonCurrentLiabilities": "211100000", "totalShareholderEquity": "1454600000", "treasuryStock": "None", "retainedEarnings": "-880100000", "commonStock": "2340800000", "commonStockSharesOutstanding": "566400000"}, {"fiscalDateEnding": "2019-01-31", "reportedCurrency": "USD", "totalAssets": "5707500000", "totalCurrentAssets": "3487500000", "cashAndCashEquivalentsAtCarryingValue": "1127800000", "cashAndShortTermInvestments": "1127800000", "inventory": "1", "currentNetReceivables": "None", "totalNonCurrentAssets": "2220000000", "propertyPlantEquipment": "273200000", "accumulatedDepreciationAmortizationPPE": "None", "intangibleAssets": "171800000", "intangibleAssetsExcludingGoodwill": "171800000", "goodwill": "636400000", "investments": "None", "longTermInvestments": "808600000", "shortTermInvestments": "1702200000", "otherCurrentAssets": "242500000", "otherNonCurrentAssets": "None", "totalLiabilities": "4632900000", "totalCurrentLiabilities": "1868200000", "currentAccountsPayable": "None", "deferredRevenue": "None", "currentDebt": "None", "shortTermDebt": "156300000", "totalNonCurrentLiabilities": "2764700000", "capitalLeaseObligations": "None", "longTermDebt": "1399500000", "currentLongTermDebt": "156300000", "longTermDebtNoncurrent": "None", "shortLongTermDebtTotal": "1555800000", "otherCurrentLiabilities": "314800000", "otherNonCurrentLiabilities": "208700000", "totalShareholderEquity": "1074600000", "treasuryStock": "None", "retainedEarnings": "-859900000", "commonStock": "1941500000", "commonStockSharesOutstanding": "564000000"}, {"fiscalDateEnding": "2018-10-31", "reportedCurrency": "USD", "totalAssets": "5801500000", "totalCurrentAssets": "3815200000", "cashAndCashEquivalentsAtCarryingValue": "1784400000", "cashAndShortTermInvestments": "1784400000", "inventory": "1", "currentNetReceivables": "None", "totalNonCurrentAssets": "1986300000", "propertyPlantEquipment": "276500000", "accumulatedDepreciationAmortizationPPE": "None", "intangibleAssets": "186200000", "intangibleAssetsExcludingGoodwill": "186200000", "goodwill": "636400000", "investments": "None", "longTermInvestments": "565500000", "shortTermInvestments": "1419400000", "otherCurrentAssets": "229100000", "otherNonCurrentAssets": "None", "totalLiabilities": "4541600000", "totalCurrentLiabilities": "1815700000", "currentAccountsPayable": "None", "deferredRevenue": "None", "currentDebt": "None", "shortTermDebt": "239900000", "totalNonCurrentLiabilities": "2725900000", "capitalLeaseObligations": "None", "longTermDebt": "1384500000", "currentLongTermDebt": "239900000", "longTermDebtNoncurrent": "None", "shortLongTermDebtTotal": "1624400000", "otherCurrentLiabilities": "263000000", "otherNonCurrentLiabilities": "226800000", "totalShareholderEquity": "1259900000", "treasuryStock": "0", "retainedEarnings": "-857300000", "commonStock": "2129300000", "commonStockSharesOutstanding": "562800000"}, {"fiscalDateEnding": "2018-07-31", "reportedCurrency": "USD", "totalAssets": "5823000000", "totalCurrentAssets": "4132000000", "cashAndCashEquivalentsAtCarryingValue": "2506900000", "cashAndShortTermInvestments": "2506900000", "inventory": "1", "currentNetReceivables": "None", "totalNonCurrentAssets": "1691000000", "propertyPlantEquipment": "273100000", "accumulatedDepreciationAmortizationPPE": "None", "intangibleAssets": "140800000", "intangibleAssetsExcludingGoodwill": "140800000", "goodwill": "522800000", "investments": "None", "longTermInvestments": "547500000", "shortTermInvestments": "896500000", "otherCurrentAssets": "261300000", "otherNonCurrentAssets": "None", "totalLiabilities": "4834700000", "totalCurrentLiabilities": "2139400000", "currentAccountsPayable": "None", "deferredRevenue": "None", "currentDebt": "None", "shortTermDebt": "550400000", "totalNonCurrentLiabilities": "2695300000", "capitalLeaseObligations": "None", "longTermDebt": "1369700000", "currentLongTermDebt": "550400000", "longTermDebtNoncurrent": "None", "shortLongTermDebtTotal": "1920100000", "otherCurrentLiabilities": "270700000", "otherNonCurrentLiabilities": "229600000", "totalShareholderEquity": "988300000", "treasuryStock": "0", "retainedEarnings": "-984600000", "commonStock": "1967400000", "commonStockSharesOutstanding": "556800000"}, {"fiscalDateEnding": "2018-04-30", "reportedCurrency": "USD", "totalAssets": "3908300000", "totalCurrentAssets": "2205500000", "cashAndCashEquivalentsAtCarryingValue": "949000000", "cashAndShortTermInvestments": "949000000", "inventory": "1", "currentNetReceivables": "None", "totalNonCurrentAssets": "1702800000", "propertyPlantEquipment": "264200000", "accumulatedDepreciationAmortizationPPE": "None", "intangibleAssets": "147700000", "intangibleAssetsExcludingGoodwill": "147700000", "goodwill": "522200000", "investments": "None", "longTermInvestments": "592900000", "shortTermInvestments": "672200000", "otherCurrentAssets": "222500000", "otherNonCurrentAssets": "None", "totalLiabilities": "3158500000", "totalCurrentLiabilities": "1943100000", "currentAccountsPayable": "None", "deferredRevenue": "None", "currentDebt": "None", "shortTermDebt": "543800000", "totalNonCurrentLiabilities": "1215400000", "capitalLeaseObligations": "None", "longTermDebt": "0", "currentLongTermDebt": "543800000", "longTermDebtNoncurrent": "None", "shortLongTermDebtTotal": "543800000", "otherCurrentLiabilities": "201100000", "otherNonCurrentLiabilities": "226000000", "totalShareholderEquity": "749800000", "treasuryStock": "0", "retainedEarnings": "-982300000", "commonStock": "1717600000", "commonStockSharesOutstanding": "551400000"}, {"fiscalDateEnding": "2018-01-31", "reportedCurrency": "USD", "totalAssets": "3627500000", "totalCurrentAssets": "2210200000", "cashAndCashEquivalentsAtCarryingValue": "915000000", "cashAndShortTermInvestments": "915000000", "inventory": "1", "currentNetReceivables": "None", "totalNonCurrentAssets": "1417300000", "propertyPlantEquipment": "264700000", "accumulatedDepreciationAmortizationPPE": "None", "intangibleAssets": "48300000", "intangibleAssetsExcludingGoodwill": "48300000", "goodwill": "238800000", "investments": "None", "longTermInvestments": "722300000", "shortTermInvestments": "720700000", "otherCurrentAssets": "209400000", "otherNonCurrentAssets": "None", "totalLiabilities": "2960900000", "totalCurrentLiabilities": "1856400000", "currentAccountsPayable": "None", "deferredRevenue": "None", "currentDebt": "None", "shortTermDebt": "537400000", "totalNonCurrentLiabilities": "1104500000", "capitalLeaseObligations": "None", "longTermDebt": "0", "currentLongTermDebt": "537400000", "longTermDebtNoncurrent": "None", "shortLongTermDebtTotal": "537400000", "otherCurrentLiabilities": "196800000", "otherNonCurrentLiabilities": "196600000", "totalShareholderEquity": "666600000", "treasuryStock": "0", "retainedEarnings": "-935600000", "commonStock": "1575900000", "commonStockSharesOutstanding": "546600000"}, {"fiscalDateEnding": "2017-10-31", "reportedCurrency": "USD", "totalAssets": "3486500000", "totalCurrentAssets": "2039500000", "cashAndCashEquivalentsAtCarryingValue": "842600000", "cashAndShortTermInvestments": "842600000", "inventory": "0", "currentNetReceivables": "None", "totalNonCurrentAssets": "1447000000", "propertyPlantEquipment": "256900000", "accumulatedDepreciationAmortizationPPE": "None", "intangibleAssets": "51000000", "intangibleAssetsExcludingGoodwill": "51000000", "goodwill": "238800000", "investments": "None", "longTermInvestments": "777400000", "shortTermInvestments": "660600000", "otherCurrentAssets": "185500000", "otherNonCurrentAssets": "None", "totalLiabilities": "2781800000", "totalCurrentLiabilities": "1743000000", "currentAccountsPayable": "None", "deferredRevenue": "None", "currentDebt": "None", "shortTermDebt": "531000000", "totalNonCurrentLiabilities": "1038800000", "capitalLeaseObligations": "None", "longTermDebt": "0", "currentLongTermDebt": "531000000", "longTermDebtNoncurrent": "None", "shortLongTermDebtTotal": "531000000", "otherCurrentLiabilities": "155300000", "otherNonCurrentLiabilities": "192200000", "totalShareholderEquity": "704700000", "treasuryStock": "0", "retainedEarnings": "-900700000", "commonStock": "1573200000", "commonStockSharesOutstanding": "545400000"}, {"fiscalDateEnding": "2017-07-31", "reportedCurrency": "USD", "totalAssets": "3438300000", "totalCurrentAssets": "1976300000", "cashAndCashEquivalentsAtCarryingValue": "744300000", "cashAndShortTermInvestments": "744300000", "inventory": "1", "currentNetReceivables": "None", "totalNonCurrentAssets": "1462000000", "propertyPlantEquipment": "211100000", "accumulatedDepreciationAmortizationPPE": "None", "intangibleAssets": "53700000", "intangibleAssetsExcludingGoodwill": "53700000", "goodwill": "238800000", "investments": "None", "longTermInvestments": "789300000", "shortTermInvestments": "630700000", "otherCurrentAssets": "169200000", "otherNonCurrentAssets": "None", "totalLiabilities": "2678700000", "totalCurrentLiabilities": "1201300000", "currentAccountsPayable": "None", "deferredRevenue": "None", "currentDebt": "None", "shortTermDebt": "524700000", "totalNonCurrentLiabilities": "1477400000", "capitalLeaseObligations": "None", "longTermDebt": "524700000", "currentLongTermDebt": "524700000", "longTermDebtNoncurrent": "None", "shortLongTermDebtTotal": "524700000", "otherCurrentLiabilities": "197400000", "otherNonCurrentLiabilities": "147600000", "totalShareholderEquity": "759600000", "treasuryStock": "0", "retainedEarnings": "-836700000", "commonStock": "1599700000", "commonStockSharesOutstanding": "545400000"}, {"fiscalDateEnding": "2017-04-30", "reportedCurrency": "USD", "totalAssets": "3250100000", "totalCurrentAssets": "1895200000", "cashAndCashEquivalentsAtCarryingValue": "692000000", "cashAndShortTermInvestments": "692000000", "inventory": "0", "currentNetReceivables": "None", "totalNonCurrentAssets": "1354900000", "propertyPlantEquipment": "192300000", "accumulatedDepreciationAmortizationPPE": "None", "intangibleAssets": "56500000", "intangibleAssetsExcludingGoodwill": "56500000", "goodwill": "238800000", "investments": "None", "longTermInvestments": "719100000", "shortTermInvestments": "680000000", "otherCurrentAssets": "159100000", "otherNonCurrentAssets": "None", "totalLiabilities": "2437000000", "totalCurrentLiabilities": "1054700000", "currentAccountsPayable": "None", "deferredRevenue": "None", "currentDebt": "None", "shortTermDebt": "None", "totalNonCurrentLiabilities": "1382300000", "capitalLeaseObligations": "None", "longTermDebt": "518400000", "currentLongTermDebt": "None", "longTermDebtNoncurrent": "None", "shortLongTermDebtTotal": "518400000", "otherCurrentLiabilities": "136500000", "otherNonCurrentLiabilities": "137100000", "totalShareholderEquity": "813100000", "treasuryStock": "0", "retainedEarnings": "-798500000", "commonStock": "1615800000", "commonStockSharesOutstanding": "546000000"}, {"fiscalDateEnding": "2017-01-31", "reportedCurrency": "USD", "totalAssets": "3174600000", "totalCurrentAssets": "1880400000", "cashAndCashEquivalentsAtCarryingValue": "761400000", "cashAndShortTermInvestments": "761400000", "inventory": "1", "currentNetReceivables": "None", "totalNonCurrentAssets": "1294200000", "propertyPlantEquipment": "154100000", "accumulatedDepreciationAmortizationPPE": "None", "intangibleAssets": "39500000", "intangibleAssetsExcludingGoodwill": "39500000", "goodwill": "163500000", "investments": "None", "longTermInvestments": "790500000", "shortTermInvestments": "593000000", "otherCurrentAssets": "139900000", "otherNonCurrentAssets": "None", "totalLiabilities": "2304000000", "totalCurrentLiabilities": "993600000", "currentAccountsPayable": "None", "deferredRevenue": "None", "currentDebt": "None", "shortTermDebt": "None", "totalNonCurrentLiabilities": "1310400000", "capitalLeaseObligations": "None", "longTermDebt": "512300000", "currentLongTermDebt": "None", "longTermDebtNoncurrent": "None", "shortLongTermDebtTotal": "512300000", "otherCurrentLiabilities": "137600000", "otherNonCurrentLiabilities": "127500000", "totalShareholderEquity": "870600000", "treasuryStock": "0", "retainedEarnings": "-737600000", "commonStock": "1613300000", "commonStockSharesOutstanding": "544200000"}, {"fiscalDateEnding": "2016-10-31", "reportedCurrency": "USD", "totalAssets": "3006500000", "totalCurrentAssets": "1865900000", "cashAndCashEquivalentsAtCarryingValue": "839400000", "cashAndShortTermInvestments": "839400000", "inventory": "1", "currentNetReceivables": "None", "totalNonCurrentAssets": "1140600000", "propertyPlantEquipment": "125000000", "accumulatedDepreciationAmortizationPPE": "None", "intangibleAssets": "41700000", "intangibleAssetsExcludingGoodwill": "41700000", "goodwill": "163500000", "investments": "None", "longTermInvestments": "708400000", "shortTermInvestments": "550600000", "otherCurrentAssets": "129400000", "otherNonCurrentAssets": "None", "totalLiabilities": "2088200000", "totalCurrentLiabilities": "1400900000", "currentAccountsPayable": "None", "deferredRevenue": "None", "currentDebt": "None", "shortTermDebt": "506200000", "totalNonCurrentLiabilities": "687300000", "capitalLeaseObligations": "None", "longTermDebt": "0", "currentLongTermDebt": "506200000", "longTermDebtNoncurrent": "None", "shortLongTermDebtTotal": "506200000", "otherCurrentLiabilities": "107400000", "otherNonCurrentLiabilities": "85800000", "totalShareholderEquity": "918300000", "treasuryStock": "0", "retainedEarnings": "-683400000", "commonStock": "1542200000", "commonStockSharesOutstanding": "538800000"}, {"fiscalDateEnding": "2016-07-31", "reportedCurrency": "USD", "totalAssets": "2761200000", "totalCurrentAssets": "1719100000", "cashAndCashEquivalentsAtCarryingValue": "734400000", "cashAndShortTermInvestments": "734400000", "inventory": "1", "currentNetReceivables": "None", "totalNonCurrentAssets": "1042100000", "propertyPlantEquipment": "117200000", "accumulatedDepreciationAmortizationPPE": "None", "intangibleAssets": "44000000", "intangibleAssetsExcludingGoodwill": "44000000", "goodwill": "163500000", "investments": "None", "longTermInvestments": "652800000", "shortTermInvestments": "551200000", "otherCurrentAssets": "84800000", "otherNonCurrentAssets": "None", "totalLiabilities": "1971300000", "totalCurrentLiabilities": "846800000", "currentAccountsPayable": "None", "deferredRevenue": "None", "currentDebt": "None", "shortTermDebt": "500200000", "totalNonCurrentLiabilities": "1124500000", "capitalLeaseObligations": "None", "longTermDebt": "508200000", "currentLongTermDebt": "500200000", "longTermDebtNoncurrent": "None", "shortLongTermDebtTotal": "1008400000", "otherCurrentLiabilities": "112700000", "otherNonCurrentLiabilities": "79400000", "totalShareholderEquity": "789900000", "treasuryStock": "0", "retainedEarnings": "-726600000", "commonStock": "1515500000", "commonStockSharesOutstanding": "533400000"}, {"fiscalDateEnding": "2016-04-30", "reportedCurrency": "USD", "totalAssets": "2507000000", "totalCurrentAssets": "1446200000", "cashAndCashEquivalentsAtCarryingValue": "550000000", "cashAndShortTermInvestments": "550000000", "inventory": "0", "currentNetReceivables": "None", "totalNonCurrentAssets": "1060800000", "propertyPlantEquipment": "100500000", "accumulatedDepreciationAmortizationPPE": "None", "intangibleAssets": "46400000", "intangibleAssetsExcludingGoodwill": "46400000", "goodwill": "163500000", "investments": "None", "longTermInvestments": "682900000", "shortTermInvestments": "537500000", "otherCurrentAssets": "91100000", "otherNonCurrentAssets": "None", "totalLiabilities": "1775800000", "totalCurrentLiabilities": "1239000000", "currentAccountsPayable": "None", "deferredRevenue": "None", "currentDebt": "None", "shortTermDebt": "502800000", "totalNonCurrentLiabilities": "536800000", "capitalLeaseObligations": "None", "longTermDebt": "0", "currentLongTermDebt": "502800000", "longTermDebtNoncurrent": "None", "shortLongTermDebtTotal": "502800000", "otherCurrentLiabilities": "101500000", "otherNonCurrentLiabilities": "78000000", "totalShareholderEquity": "731200000", "treasuryStock": "0", "retainedEarnings": "-672100000", "commonStock": "1330500000", "commonStockSharesOutstanding": "526800000"}, {"fiscalDateEnding": "2016-01-31", "reportedCurrency": "USD", "totalAssets": "2316600000", "totalCurrentAssets": "1307100000", "cashAndCashEquivalentsAtCarryingValue": "413200000", "cashAndShortTermInvestments": "413200000", "inventory": "1", "currentNetReceivables": "None", "totalNonCurrentAssets": "1009500000", "propertyPlantEquipment": "92600000", "accumulatedDepreciationAmortizationPPE": "None", "intangibleAssets": "48700000", "intangibleAssetsExcludingGoodwill": "48700000", "goodwill": "163500000", "investments": "None", "longTermInvestments": "631100000", "shortTermInvestments": "551400000", "otherCurrentAssets": "88100000", "otherNonCurrentAssets": "None", "totalLiabilities": "1646300000", "totalCurrentLiabilities": "1186400000", "currentAccountsPayable": "None", "deferredRevenue": "None", "currentDebt": "None", "shortTermDebt": "497500000", "totalNonCurrentLiabilities": "459900000", "capitalLeaseObligations": "None", "longTermDebt": "0", "currentLongTermDebt": "None", "longTermDebtNoncurrent": "None", "shortLongTermDebtTotal": "497500000", "otherCurrentLiabilities": "115200000", "otherNonCurrentLiabilities": "72300000", "totalShareholderEquity": "670300000", "treasuryStock": "0", "retainedEarnings": "-601900000", "commonStock": "1195400000", "commonStockSharesOutstanding": "519600000"}, {"fiscalDateEnding": "2015-10-31", "reportedCurrency": "USD", "totalAssets": "2094400000", "totalCurrentAssets": "1039900000", "cashAndCashEquivalentsAtCarryingValue": "275800000", "cashAndShortTermInvestments": "275800000", "inventory": "0", "currentNetReceivables": "None", "totalNonCurrentAssets": "1054500000", "propertyPlantEquipment": "76700000", "accumulatedDepreciationAmortizationPPE": "None", "intangibleAssets": "51000000", "intangibleAssetsExcludingGoodwill": "51000000", "goodwill": "163500000", "investments": "None", "longTermInvestments": "694500000", "shortTermInvestments": "485500000", "otherCurrentAssets": "82200000", "otherNonCurrentAssets": "None", "totalLiabilities": "1467900000", "totalCurrentLiabilities": "1078200000", "currentAccountsPayable": "None", "deferredRevenue": "None", "currentDebt": "None", "shortTermDebt": "492300000", "totalNonCurrentLiabilities": "389700000", "capitalLeaseObligations": "None", "longTermDebt": "0", "currentLongTermDebt": "None", "longTermDebtNoncurrent": "None", "shortLongTermDebtTotal": "492300000", "otherCurrentLiabilities": "91100000", "otherNonCurrentLiabilities": "62500000", "totalShareholderEquity": "626500000", "treasuryStock": "0", "retainedEarnings": "-539400000", "commonStock": "1083600000", "commonStockSharesOutstanding": "510600000"}, {"fiscalDateEnding": "2015-07-31", "reportedCurrency": "USD", "totalAssets": "1965178000", "totalCurrentAssets": "1074030000", "cashAndCashEquivalentsAtCarryingValue": "375814000", "cashAndShortTermInvestments": "375814000", "inventory": "0", "currentNetReceivables": "None", "totalNonCurrentAssets": "891148000", "propertyPlantEquipment": "62878000", "accumulatedDepreciationAmortizationPPE": "None", "intangibleAssets": "52656000", "intangibleAssetsExcludingGoodwill": "52656000", "goodwill": "163522000", "investments": "None", "longTermInvestments": "538841000", "shortTermInvestments": "413165000", "otherCurrentAssets": "72685000", "otherNonCurrentAssets": "None", "totalLiabilities": "1389363000", "totalCurrentLiabilities": "1032227000", "currentAccountsPayable": "None", "deferredRevenue": "None", "currentDebt": "None", "shortTermDebt": "487084000", "totalNonCurrentLiabilities": "357136000", "capitalLeaseObligations": "None", "longTermDebt": "0", "currentLongTermDebt": "487100000", "longTermDebtNoncurrent": "None", "shortLongTermDebtTotal": "487084000", "otherCurrentLiabilities": "108086000", "otherNonCurrentLiabilities": "67335000", "totalShareholderEquity": "575815000", "treasuryStock": "0", "retainedEarnings": "-500708000", "commonStock": "8000", "commonStockSharesOutstanding": "503808000"}, {"fiscalDateEnding": "2015-04-30", "reportedCurrency": "USD", "totalAssets": "1784432000", "totalCurrentAssets": "1040509000", "cashAndCashEquivalentsAtCarryingValue": "454123000", "cashAndShortTermInvestments": "454123000", "inventory": "1", "currentNetReceivables": "None", "totalNonCurrentAssets": "743923000", "propertyPlantEquipment": "59546000", "accumulatedDepreciationAmortizationPPE": "None", "intangibleAssets": "43885000", "intangibleAssetsExcludingGoodwill": "43885000", "goodwill": "155402000", "investments": "None", "longTermInvestments": "408465000", "shortTermInvestments": "368850000", "otherCurrentAssets": "67013000", "otherNonCurrentAssets": "None", "totalLiabilities": "1237114000", "totalCurrentLiabilities": "944007000", "currentAccountsPayable": "None", "deferredRevenue": "None", "currentDebt": "None", "shortTermDebt": "481960000", "totalNonCurrentLiabilities": "293107000", "capitalLeaseObligations": "None", "longTermDebt": "0", "currentLongTermDebt": "None", "longTermDebtNoncurrent": "None", "shortLongTermDebtTotal": "481960000", "otherCurrentLiabilities": "82002000", "otherNonCurrentLiabilities": "54601000", "totalShareholderEquity": "547318000", "treasuryStock": "0", "retainedEarnings": "-454737000", "commonStock": "8000", "commonStockSharesOutstanding": "493800000"}, {"fiscalDateEnding": "2015-01-31", "reportedCurrency": "USD", "totalAssets": "1672784000", "totalCurrentAssets": "861504000", "cashAndCashEquivalentsAtCarryingValue": "342983000", "cashAndShortTermInvestments": "342983000", "inventory": "1", "currentNetReceivables": "None", "totalNonCurrentAssets": "811280000", "propertyPlantEquipment": "52639000", "accumulatedDepreciationAmortizationPPE": "None", "intangibleAssets": "45856000", "intangibleAssetsExcludingGoodwill": "45856000", "goodwill": "155402000", "investments": "None", "longTermInvestments": "463908000", "shortTermInvestments": "332074000", "otherCurrentAssets": "51196000", "otherNonCurrentAssets": "None", "totalLiabilities": "1156723000", "totalCurrentLiabilities": "415074000", "currentAccountsPayable": "None", "deferredRevenue": "None", "currentDebt": "None", "shortTermDebt": "None", "totalNonCurrentLiabilities": "741649000", "capitalLeaseObligations": "None", "longTermDebt": "476872000", "currentLongTermDebt": "None", "longTermDebtNoncurrent": "None", "shortLongTermDebtTotal": "476872000", "otherCurrentLiabilities": "76594000", "otherNonCurrentLiabilities": "53413000", "totalShareholderEquity": "516061000", "treasuryStock": "0", "retainedEarnings": "-408802000", "commonStock": "8000", "commonStockSharesOutstanding": "484800000"}, {"fiscalDateEnding": "2014-10-31", "reportedCurrency": "USD", "totalAssets": "1540356000", "totalCurrentAssets": "933567000", "cashAndCashEquivalentsAtCarryingValue": "543747000", "cashAndShortTermInvestments": "543747000", "inventory": "0", "currentNetReceivables": "None", "totalNonCurrentAssets": "606789000", "propertyPlantEquipment": "49823000", "accumulatedDepreciationAmortizationPPE": "None", "intangibleAssets": "47451000", "intangibleAssetsExcludingGoodwill": "47451000", "goodwill": "155033000", "investments": "None", "longTermInvestments": "289011000", "shortTermInvestments": "227752000", "otherCurrentAssets": "45844000", "otherNonCurrentAssets": "None", "totalLiabilities": "1047145000", "totalCurrentLiabilities": "360966000", "currentAccountsPayable": "None", "deferredRevenue": "None", "currentDebt": "None", "shortTermDebt": "None", "totalNonCurrentLiabilities": "686179000", "capitalLeaseObligations": "None", "longTermDebt": "471856000", "currentLongTermDebt": "None", "longTermDebtNoncurrent": "None", "shortLongTermDebtTotal": "471856000", "otherCurrentLiabilities": "63787000", "otherNonCurrentLiabilities": "30285000", "totalShareholderEquity": "493211000", "treasuryStock": "0", "retainedEarnings": "-365794000", "commonStock": "8000", "commonStockSharesOutstanding": "476400000"}, {"fiscalDateEnding": "2014-07-31", "reportedCurrency": "USD", "totalAssets": "1478466000", "totalCurrentAssets": "958326000", "cashAndCashEquivalentsAtCarryingValue": "653812000", "cashAndShortTermInvestments": "653812000", "inventory": "0", "currentNetReceivables": "None", "totalNonCurrentAssets": "520140000", "propertyPlantEquipment": "48744000", "accumulatedDepreciationAmortizationPPE": "None", "intangibleAssets": "47955000", "intangibleAssetsExcludingGoodwill": "47955000", "goodwill": "155033000", "investments": "None", "longTermInvestments": "201880000", "shortTermInvestments": "118690000", "otherCurrentAssets": "50306000", "otherNonCurrentAssets": "None", "totalLiabilities": "1009883000", "totalCurrentLiabilities": "348171000", "currentAccountsPayable": "None", "deferredRevenue": "None", "currentDebt": "None", "shortTermDebt": "60937000", "totalNonCurrentLiabilities": "661712000", "capitalLeaseObligations": "None", "longTermDebt": "466875000", "currentLongTermDebt": "466875000", "longTermDebtNoncurrent": "None", "shortLongTermDebtTotal": "527812000", "otherCurrentLiabilities": "12790000", "otherNonCurrentLiabilities": "32177000", "totalShareholderEquity": "468583000", "treasuryStock": "0", "retainedEarnings": "-335726000", "commonStock": "8000", "commonStockSharesOutstanding": "467154000"}, {"fiscalDateEnding": "2014-04-30", "reportedCurrency": "USD", "totalAssets": "880387000", "totalCurrentAssets": "516445000", "cashAndCashEquivalentsAtCarryingValue": "234790000", "cashAndShortTermInvestments": "234790000", "inventory": "0", "currentNetReceivables": "None", "totalNonCurrentAssets": "363942000", "propertyPlantEquipment": "48488000", "accumulatedDepreciationAmortizationPPE": "None", "intangibleAssets": "49613000", "intangibleAssetsExcludingGoodwill": "49613000", "goodwill": "155086000", "investments": "None", "longTermInvestments": "103902000", "shortTermInvestments": "133180000", "otherCurrentAssets": "33686000", "otherNonCurrentAssets": "None", "totalLiabilities": "601222000", "totalCurrentLiabilities": "427879000", "currentAccountsPayable": "None", "deferredRevenue": "None", "currentDebt": "None", "shortTermDebt": "7473000", "totalNonCurrentLiabilities": "173343000", "capitalLeaseObligations": "None", "longTermDebt": "0", "currentLongTermDebt": "None", "longTermDebtNoncurrent": "None", "shortLongTermDebtTotal": "None", "otherCurrentLiabilities": "179484000", "otherNonCurrentLiabilities": "36636000", "totalShareholderEquity": "279165000", "treasuryStock": "0", "retainedEarnings": "-296196000", "commonStock": "7000", "commonStockSharesOutstanding": "449802000"}, {"fiscalDateEnding": "2014-01-31", "reportedCurrency": "USD", "totalAssets": "689026000", "totalCurrentAssets": "555287000", "cashAndCashEquivalentsAtCarryingValue": "261867000", "cashAndShortTermInvestments": "261867000", "inventory": "0", "currentNetReceivables": "None", "totalNonCurrentAssets": "133739000", "propertyPlantEquipment": "45735000", "accumulatedDepreciationAmortizationPPE": "None", "intangibleAssets": "18227000", "intangibleAssetsExcludingGoodwill": "18227000", "goodwill": "10094000", "investments": "None", "longTermInvestments": "63105000", "shortTermInvestments": "176345000", "otherCurrentAssets": "30985000", "otherNonCurrentAssets": "None", "totalLiabilities": "404582000", "totalCurrentLiabilities": "262809000", "currentAccountsPayable": "None", "deferredRevenue": "None", "currentDebt": "None", "shortTermDebt": "None", "totalNonCurrentLiabilities": "141773000", "capitalLeaseObligations": "None", "longTermDebt": "0", "currentLongTermDebt": "None", "longTermDebtNoncurrent": "None", "shortLongTermDebtTotal": "None", "otherCurrentLiabilities": "50138000", "otherNonCurrentLiabilities": "19512000", "totalShareholderEquity": "284444000", "treasuryStock": "0", "retainedEarnings": "-157081000", "commonStock": "7000", "commonStockSharesOutstanding": "437124000"}, {"fiscalDateEnding": "2013-10-31", "reportedCurrency": "USD", "totalAssets": "639943000", "totalCurrentAssets": "552332000", "cashAndCashEquivalentsAtCarryingValue": "266182000", "cashAndShortTermInvestments": "266182000", "inventory": "1", "currentNetReceivables": "None", "totalNonCurrentAssets": "87611000", "propertyPlantEquipment": "42409000", "accumulatedDepreciationAmortizationPPE": "None", "intangibleAssets": "6203000", "intangibleAssetsExcludingGoodwill": "6203000", "goodwill": "0", "investments": "None", "longTermInvestments": "33642000", "shortTermInvestments": "170551000", "otherCurrentAssets": "24160000", "otherNonCurrentAssets": "None", "totalLiabilities": "350164000", "totalCurrentLiabilities": "228329000", "currentAccountsPayable": "None", "deferredRevenue": "None", "currentDebt": "None", "shortTermDebt": "None", "totalNonCurrentLiabilities": "121835000", "capitalLeaseObligations": "None", "longTermDebt": "0", "currentLongTermDebt": "None", "longTermDebtNoncurrent": "None", "shortLongTermDebtTotal": "None", "otherCurrentLiabilities": "41494000", "otherNonCurrentLiabilities": "14496000", "totalShareholderEquity": "289779000", "treasuryStock": "0", "retainedEarnings": "-117135000", "commonStock": "7000", "commonStockSharesOutstanding": "430086000"}, {"fiscalDateEnding": "2013-07-31", "reportedCurrency": "USD", "totalAssets": "585606000", "totalCurrentAssets": "529699000", "cashAndCashEquivalentsAtCarryingValue": "310614000", "cashAndShortTermInvestments": "310614000", "inventory": "0", "currentNetReceivables": "None", "totalNonCurrentAssets": "55907000", "propertyPlantEquipment": "32086000", "accumulatedDepreciationAmortizationPPE": "None", "intangibleAssets": "1358000", "intangibleAssetsExcludingGoodwill": "1358000", "goodwill": "0", "investments": "None", "longTermInvestments": "17314000", "shortTermInvestments": "109007000", "otherCurrentAssets": "22617000", "otherNonCurrentAssets": "None", "totalLiabilities": "313186000", "totalCurrentLiabilities": "206102000", "currentAccountsPayable": "None", "deferredRevenue": "None", "currentDebt": "None", "shortTermDebt": "35757000", "totalNonCurrentLiabilities": "107084000", "capitalLeaseObligations": "None", "longTermDebt": "0", "currentLongTermDebt": "None", "longTermDebtNoncurrent": "None", "shortLongTermDebtTotal": "None", "otherCurrentLiabilities": "856000", "otherNonCurrentLiabilities": "11799000", "totalShareholderEquity": "272420000", "treasuryStock": "0", "retainedEarnings": "-109274000", "commonStock": "7000", "commonStockSharesOutstanding": "425616000"}, {"fiscalDateEnding": "2013-04-30", "reportedCurrency": "USD", "totalAssets": "538777000", "totalCurrentAssets": "472724000", "cashAndCashEquivalentsAtCarryingValue": "213664000", "cashAndShortTermInvestments": "213664000", "inventory": "0", "currentNetReceivables": "None", "totalNonCurrentAssets": "66053000", "propertyPlantEquipment": "29500000", "accumulatedDepreciationAmortizationPPE": "None", "intangibleAssets": "1415000", "intangibleAssetsExcludingGoodwill": "1415000", "goodwill": "0", "investments": "None", "longTermInvestments": "29767000", "shortTermInvestments": "148033000", "otherCurrentAssets": "19538000", "otherNonCurrentAssets": "None", "totalLiabilities": "274896000", "totalCurrentLiabilities": "182018000", "currentAccountsPayable": "None", "deferredRevenue": "None", "currentDebt": "None", "shortTermDebt": "None", "totalNonCurrentLiabilities": "92878000", "capitalLeaseObligations": "None", "longTermDebt": "0", "currentLongTermDebt": "None", "longTermDebtNoncurrent": "None", "shortLongTermDebtTotal": "None", "otherCurrentLiabilities": "35240000", "otherNonCurrentLiabilities": "7542000", "totalShareholderEquity": "263881000", "treasuryStock": "0", "retainedEarnings": "-93438000", "commonStock": "7000", "commonStockSharesOutstanding": "417450000"}, {"fiscalDateEnding": "2013-01-31", "reportedCurrency": "USD", "totalAssets": "490149000", "totalCurrentAssets": "426674000", "cashAndCashEquivalentsAtCarryingValue": "187924000", "cashAndShortTermInvestments": "187924000", "inventory": "1", "currentNetReceivables": "None", "totalNonCurrentAssets": "63475000", "propertyPlantEquipment": "25980000", "accumulatedDepreciationAmortizationPPE": "None", "intangibleAssets": "957000", "intangibleAssetsExcludingGoodwill": "957000", "goodwill": "0", "investments": "None", "longTermInvestments": "30871000", "shortTermInvestments": "149520000", "otherCurrentAssets": "20644000", "otherNonCurrentAssets": "None", "totalLiabilities": "246629000", "totalCurrentLiabilities": "168996000", "currentAccountsPayable": "None", "deferredRevenue": "None", "currentDebt": "None", "shortTermDebt": "None", "totalNonCurrentLiabilities": "77633000", "capitalLeaseObligations": "None", "longTermDebt": "0", "currentLongTermDebt": "None", "longTermDebtNoncurrent": "None", "shortLongTermDebtTotal": "None", "otherCurrentLiabilities": "40790000", "otherNonCurrentLiabilities": "6887000", "totalShareholderEquity": "243520000", "treasuryStock": "0", "retainedEarnings": "-86156000", "commonStock": "7000", "commonStockSharesOutstanding": "405906000"}, {"fiscalDateEnding": "2012-10-31", "reportedCurrency": "USD", "totalAssets": "444297000", "totalCurrentAssets": "394739000", "cashAndCashEquivalentsAtCarryingValue": "174473000", "cashAndShortTermInvestments": "174473000", "inventory": "1", "currentNetReceivables": "None", "totalNonCurrentAssets": "49558000", "propertyPlantEquipment": "22965000", "accumulatedDepreciationAmortizationPPE": "None", "intangibleAssets": "0", "intangibleAssetsExcludingGoodwill": "0", "goodwill": "0", "investments": "None", "longTermInvestments": "20567000", "shortTermInvestments": "147084000", "otherCurrentAssets": "16813000", "otherNonCurrentAssets": "None", "totalLiabilities": "208508000", "totalCurrentLiabilities": "142616000", "currentAccountsPayable": "None", "deferredRevenue": "None", "currentDebt": "None", "shortTermDebt": "None", "totalNonCurrentLiabilities": "65892000", "capitalLeaseObligations": "None", "longTermDebt": "0", "currentLongTermDebt": "None", "longTermDebtNoncurrent": "None", "shortLongTermDebtTotal": "None", "otherCurrentLiabilities": "30914000", "otherNonCurrentLiabilities": "6896000", "totalShareholderEquity": "235789000", "treasuryStock": "0", "retainedEarnings": "-83543000", "commonStock": "7000", "commonStockSharesOutstanding": "400878000"}, {"fiscalDateEnding": "2012-07-31", "reportedCurrency": "USD", "totalAssets": "407804000", "totalCurrentAssets": "381657000", "cashAndCashEquivalentsAtCarryingValue": "322642000", "cashAndShortTermInvestments": "322642000", "inventory": "None", "currentNetReceivables": "None", "totalNonCurrentAssets": "26147000", "propertyPlantEquipment": "20979000", "accumulatedDepreciationAmortizationPPE": "None", "intangibleAssets": "483000", "intangibleAssetsExcludingGoodwill": "483000", "goodwill": "None", "investments": "None", "longTermInvestments": "None", "shortTermInvestments": "None", "otherCurrentAssets": "13373000", "otherNonCurrentAssets": "None", "totalLiabilities": "178733000", "totalCurrentLiabilities": "122006000", "currentAccountsPayable": "None", "deferredRevenue": "None", "currentDebt": "None", "shortTermDebt": "None", "totalNonCurrentLiabilities": "56727000", "capitalLeaseObligations": "None", "longTermDebt": "None", "currentLongTermDebt": "None", "longTermDebtNoncurrent": "None", "shortLongTermDebtTotal": "None", "otherCurrentLiabilities": "26496000", "otherNonCurrentLiabilities": "None", "totalShareholderEquity": "229071000", "treasuryStock": "None", "retainedEarnings": "-80028000", "commonStock": "7000", "commonStockSharesOutstanding": "155514000"}, {"fiscalDateEnding": "2012-04-30", "reportedCurrency": "USD", "totalAssets": "166489000", "totalCurrentAssets": "141616000", "cashAndCashEquivalentsAtCarryingValue": "90283000", "cashAndShortTermInvestments": "90283000", "inventory": "4306000", "currentNetReceivables": "None", "totalNonCurrentAssets": "24873000", "propertyPlantEquipment": "19613000", "accumulatedDepreciationAmortizationPPE": "None", "intangibleAssets": "None", "intangibleAssetsExcludingGoodwill": "None", "goodwill": "None", "investments": "None", "longTermInvestments": "None", "shortTermInvestments": "None", "otherCurrentAssets": "8231000", "otherNonCurrentAssets": "None", "totalLiabilities": "155586000", "totalCurrentLiabilities": "105569000", "currentAccountsPayable": "None", "deferredRevenue": "None", "currentDebt": "None", "shortTermDebt": "16663000", "totalNonCurrentLiabilities": "50017000", "capitalLeaseObligations": "None", "longTermDebt": "None", "currentLongTermDebt": "None", "longTermDebtNoncurrent": "None", "shortLongTermDebtTotal": "None", "otherCurrentLiabilities": "3597000", "otherNonCurrentLiabilities": "None", "totalShareholderEquity": "10903000", "treasuryStock": "None", "retainedEarnings": "-75911000", "commonStock": "6000", "commonStockSharesOutstanding": "399608664"}, {"fiscalDateEnding": "2012-01-31", "reportedCurrency": "USD", "totalAssets": "136657000", "totalCurrentAssets": "115650000", "cashAndCashEquivalentsAtCarryingValue": "82822000", "cashAndShortTermInvestments": "82822000", "inventory": "None", "currentNetReceivables": "None", "totalNonCurrentAssets": "21007000", "propertyPlantEquipment": "None", "accumulatedDepreciationAmortizationPPE": "None", "intangibleAssets": "None", "intangibleAssetsExcludingGoodwill": "None", "goodwill": "None", "investments": "None", "longTermInvestments": "None", "shortTermInvestments": "None", "otherCurrentAssets": "8755000", "otherNonCurrentAssets": "None", "totalLiabilities": "199213000", "totalCurrentLiabilities": "89184000", "currentAccountsPayable": "None", "deferredRevenue": "None", "currentDebt": "None", "shortTermDebt": "None", "totalNonCurrentLiabilities": "110029000", "capitalLeaseObligations": "None", "longTermDebt": "None", "currentLongTermDebt": "None", "longTermDebtNoncurrent": "None", "shortLongTermDebtTotal": "None", "otherCurrentLiabilities": "21817000", "otherNonCurrentLiabilities": "None", "totalShareholderEquity": "-62556000", "treasuryStock": "None", "retainedEarnings": "-76225000", "commonStock": "2000", "commonStockSharesOutstanding": "385968000"}, {"fiscalDateEnding": "2011-10-31", "reportedCurrency": "USD", "totalAssets": "None", "totalCurrentAssets": "None", "cashAndCashEquivalentsAtCarryingValue": "None", "cashAndShortTermInvestments": "None", "inventory": "None", "currentNetReceivables": "None", "totalNonCurrentAssets": "None", "propertyPlantEquipment": "None", "accumulatedDepreciationAmortizationPPE": "None", "intangibleAssets": "None", "intangibleAssetsExcludingGoodwill": "None", "goodwill": "None", "investments": "None", "longTermInvestments": "None", "shortTermInvestments": "None", "otherCurrentAssets": "None", "otherNonCurrentAssets": "None", "totalLiabilities": "None", "totalCurrentLiabilities": "None", "currentAccountsPayable": "None", "deferredRevenue": "None", "currentDebt": "None", "shortTermDebt": "None", "totalNonCurrentLiabilities": "None", "capitalLeaseObligations": "None", "longTermDebt": "None", "currentLongTermDebt": "None", "longTermDebtNoncurrent": "None", "shortLongTermDebtTotal": "None", "otherCurrentLiabilities": "None", "otherNonCurrentLiabilities": "None", "totalShareholderEquity": "None", "treasuryStock": "None", "retainedEarnings": "None", "commonStock": "None", "commonStockSharesOutstanding": "100290000"}, {"fiscalDateEnding": "2011-07-31", "reportedCurrency": "USD", "totalAssets": "91172000", "totalCurrentAssets": "76840000", "cashAndCashEquivalentsAtCarryingValue": "40517000", "cashAndShortTermInvestments": "40517000", "inventory": "4479000", "currentNetReceivables": "None", "totalNonCurrentAssets": "14332000", "propertyPlantEquipment": "12666000", "accumulatedDepreciationAmortizationPPE": "None", "intangibleAssets": "None", "intangibleAssetsExcludingGoodwill": "None", "goodwill": "None", "investments": "None", "longTermInvestments": "None", "shortTermInvestments": "None", "otherCurrentAssets": "2167000", "otherNonCurrentAssets": "None", "totalLiabilities": "162626000", "totalCurrentLiabilities": "67101000", "currentAccountsPayable": "None", "deferredRevenue": "None", "currentDebt": "None", "shortTermDebt": "13495000", "totalNonCurrentLiabilities": "95525000", "capitalLeaseObligations": "None", "longTermDebt": "None", "currentLongTermDebt": "None", "longTermDebtNoncurrent": "None", "shortLongTermDebtTotal": "None", "otherCurrentLiabilities": "2918000", "otherNonCurrentLiabilities": "None", "totalShareholderEquity": "-71454000", "treasuryStock": "None", "retainedEarnings": "-80765000", "commonStock": "2000", "commonStockSharesOutstanding": "100290000"}, {"fiscalDateEnding": "2011-04-30", "reportedCurrency": "USD", "totalAssets": "None", "totalCurrentAssets": "None", "cashAndCashEquivalentsAtCarryingValue": "None", "cashAndShortTermInvestments": "None", "inventory": "None", "currentNetReceivables": "None", "totalNonCurrentAssets": "None", "propertyPlantEquipment": "None", "accumulatedDepreciationAmortizationPPE": "None", "intangibleAssets": "None", "intangibleAssetsExcludingGoodwill": "None", "goodwill": "None", "investments": "None", "longTermInvestments": "None", "shortTermInvestments": "None", "otherCurrentAssets": "None", "otherNonCurrentAssets": "None", "totalLiabilities": "None", "totalCurrentLiabilities": "None", "currentAccountsPayable": "None", "deferredRevenue": "None", "currentDebt": "None", "shortTermDebt": "None", "totalNonCurrentLiabilities": "None", "capitalLeaseObligations": "None", "longTermDebt": "None", "currentLongTermDebt": "None", "longTermDebtNoncurrent": "None", "shortLongTermDebtTotal": "None", "otherCurrentLiabilities": "None", "otherNonCurrentLiabilities": "None", "totalShareholderEquity": "None", "treasuryStock": "None", "retainedEarnings": "None", "commonStock": "None", "commonStockSharesOutstanding": "100290000"}, {"fiscalDateEnding": "2010-07-31", "reportedCurrency": "USD", "totalAssets": "38119000", "totalCurrentAssets": "None", "cashAndCashEquivalentsAtCarryingValue": "18835000", "cashAndShortTermInvestments": "18835000", "inventory": "None", "currentNetReceivables": "None", "totalNonCurrentAssets": "None", "propertyPlantEquipment": "1833000", "accumulatedDepreciationAmortizationPPE": "None", "intangibleAssets": "None", "intangibleAssetsExcludingGoodwill": "None", "goodwill": "None", "investments": "None", "longTermInvestments": "None", "shortTermInvestments": "None", "otherCurrentAssets": "2584000", "otherNonCurrentAssets": "None", "totalLiabilities": "39276000", "totalCurrentLiabilities": "28660000", "currentAccountsPayable": "None", "deferredRevenue": "None", "currentDebt": "None", "shortTermDebt": "None", "totalNonCurrentLiabilities": "None", "capitalLeaseObligations": "None", "longTermDebt": "None", "currentLongTermDebt": "None", "longTermDebtNoncurrent": "None", "shortLongTermDebtTotal": "None", "otherCurrentLiabilities": "25959000", "otherNonCurrentLiabilities": "None", "totalShareholderEquity": "None", "treasuryStock": "None", "retainedEarnings": "None", "commonStock": "2000", "commonStockSharesOutstanding": "None"}]}