{"Meta Data": {"1. Information": "Daily Time Series with Splits and Dividend Events", "2. Symbol": "NVDA", "3. Last Refreshed": "2025-04-22", "4. Output Size": "Compact", "5. Time Zone": "US/Eastern"}, "Time Series (Daily)": {"2025-04-22": {"1. open": "98.78", "2. high": "99.811", "3. low": "97.28", "4. close": "98.89", "5. adjusted close": "98.89", "6. volume": "241004784", "7. dividend amount": "0.0000", "8. split coefficient": "1.0"}, "2025-04-21": {"1. open": "98.77", "2. high": "99.44", "3. low": "95.04", "4. close": "96.91", "5. adjusted close": "96.91", "6. volume": "288501136", "7. dividend amount": "0.0000", "8. split coefficient": "1.0"}, "2025-04-17": {"1. open": "104.45", "2. high": "104.47", "3. low": "100.05", "4. close": "101.49", "5. adjusted close": "101.49", "6. volume": "292517465", "7. dividend amount": "0.0000", "8. split coefficient": "1.0"}, "2025-04-16": {"1. open": "104.55", "2. high": "106.79", "3. low": "100.45", "4. close": "104.49", "5. adjusted close": "104.49", "6. volume": "397016870", "7. dividend amount": "0.0000", "8. split coefficient": "1.0"}, "2025-04-15": {"1. open": "110.97", "2. high": "113.615", "3. low": "110.5", "4. close": "112.2", "5. adjusted close": "112.2", "6. volume": "228966900", "7. dividend amount": "0.0000", "8. split coefficient": "1.0"}, "2025-04-14": {"1. open": "114.11", "2. high": "114.29", "3. low": "109.07", "4. close": "110.71", "5. adjusted close": "110.71", "6. volume": "264705049", "7. dividend amount": "0.0000", "8. split coefficient": "1.0"}, "2025-04-11": {"1. open": "108.5", "2. high": "111.5499", "3. low": "107.48", "4. close": "110.93", "5. adjusted close": "110.93", "6. volume": "313417265", "7. dividend amount": "0.0000", "8. split coefficient": "1.0"}, "2025-04-10": {"1. open": "109.37", "2. high": "110.86", "3. low": "99.15", "4. close": "107.57", "5. adjusted close": "107.57", "6. volume": "437812353", "7. dividend amount": "0.0000", "8. split coefficient": "1.0"}, "2025-04-09": {"1. open": "98.89", "2. high": "115.1", "3. low": "97.5301", "4. close": "114.33", "5. adjusted close": "114.33", "6. volume": "612918336", "7. dividend amount": "0.0000", "8. split coefficient": "1.0"}, "2025-04-08": {"1. open": "103.805", "2. high": "105.85", "3. low": "94.46", "4. close": "96.3", "5. adjusted close": "96.3", "6. volume": "476243392", "7. dividend amount": "0.0000", "8. split coefficient": "1.0"}, "2025-04-07": {"1. open": "87.46", "2. high": "101.75", "3. low": "86.62", "4. close": "97.64", "5. adjusted close": "97.64", "6. volume": "611041347", "7. dividend amount": "0.0000", "8. split coefficient": "1.0"}, "2025-04-04": {"1. open": "98.91", "2. high": "100.13", "3. low": "92.11", "4. close": "94.31", "5. adjusted close": "94.31", "6. volume": "532273810", "7. dividend amount": "0.0000", "8. split coefficient": "1.0"}, "2025-04-03": {"1. open": "103.51", "2. high": "105.63", "3. low": "101.6", "4. close": "101.8", "5. adjusted close": "101.8", "6. volume": "338769412", "7. dividend amount": "0.0000", "8. split coefficient": "1.0"}, "2025-04-02": {"1. open": "107.29", "2. high": "111.98", "3. low": "106.79", "4. close": "110.42", "5. adjusted close": "110.42", "6. volume": "220601243", "7. dividend amount": "0.0000", "8. split coefficient": "1.0"}, "2025-04-01": {"1. open": "108.515", "2. high": "110.2", "3. low": "106.47", "4. close": "110.15", "5. adjusted close": "110.15", "6. volume": "222614034", "7. dividend amount": "0.0000", "8. split coefficient": "1.0"}, "2025-03-31": {"1. open": "105.13", "2. high": "110.955", "3. low": "103.65", "4. close": "108.38", "5. adjusted close": "108.38", "6. volume": "299212653", "7. dividend amount": "0.0000", "8. split coefficient": "1.0"}, "2025-03-28": {"1. open": "111.485", "2. high": "112.87", "3. low": "109.0701", "4. close": "109.67", "5. adjusted close": "109.67", "6. volume": "229872549", "7. dividend amount": "0.0000", "8. split coefficient": "1.0"}, "2025-03-27": {"1. open": "111.35", "2. high": "114.45", "3. low": "110.66", "4. close": "111.43", "5. adjusted close": "111.43", "6. volume": "236902055", "7. dividend amount": "0.0000", "8. split coefficient": "1.0"}, "2025-03-26": {"1. open": "118.73", "2. high": "118.84", "3. low": "112.71", "4. close": "113.76", "5. adjusted close": "113.76", "6. volume": "296431667", "7. dividend amount": "0.0000", "8. split coefficient": "1.0"}, "2025-03-25": {"1. open": "120.545", "2. high": "121.29", "3. low": "118.92", "4. close": "120.69", "5. adjusted close": "120.69", "6. volume": "167447198", "7. dividend amount": "0.0000", "8. split coefficient": "1.0"}, "2025-03-24": {"1. open": "119.88", "2. high": "122.22", "3. low": "119.34", "4. close": "121.41", "5. adjusted close": "121.41", "6. volume": "228452534", "7. dividend amount": "0.0000", "8. split coefficient": "1.0"}, "2025-03-21": {"1. open": "116.94", "2. high": "117.99", "3. low": "115.42", "4. close": "117.7", "5. adjusted close": "117.7", "6. volume": "266498528", "7. dividend amount": "0.0000", "8. split coefficient": "1.0"}, "2025-03-20": {"1. open": "116.55", "2. high": "120.2", "3. low": "116.47", "4. close": "118.53", "5. adjusted close": "118.53", "6. volume": "248829749", "7. dividend amount": "0.0000", "8. split coefficient": "1.0"}, "2025-03-19": {"1. open": "117.27", "2. high": "120.445", "3. low": "115.68", "4. close": "117.52", "5. adjusted close": "117.52", "6. volume": "273426225", "7. dividend amount": "0.0000", "8. split coefficient": "1.0"}, "2025-03-18": {"1. open": "118.0", "2. high": "119.02", "3. low": "114.54", "4. close": "115.43", "5. adjusted close": "115.43", "6. volume": "299686944", "7. dividend amount": "0.0000", "8. split coefficient": "1.0"}, "2025-03-17": {"1. open": "122.74", "2. high": "122.89", "3. low": "118.03", "4. close": "119.53", "5. adjusted close": "119.53", "6. volume": "255501481", "7. dividend amount": "0.0000", "8. split coefficient": "1.0"}, "2025-03-14": {"1. open": "118.61", "2. high": "121.88", "3. low": "118.15", "4. close": "121.67", "5. adjusted close": "121.67", "6. volume": "277593455", "7. dividend amount": "0.0000", "8. split coefficient": "1.0"}, "2025-03-13": {"1. open": "117.03", "2. high": "117.76", "3. low": "113.79", "4. close": "115.58", "5. adjusted close": "115.58", "6. volume": "299033131", "7. dividend amount": "0.0000", "8. split coefficient": "1.0"}, "2025-03-12": {"1. open": "114.12", "2. high": "116.76", "3. low": "112.88", "4. close": "115.74", "5. adjusted close": "115.74", "6. volume": "323857454", "7. dividend amount": "0.0100", "8. split coefficient": "1.0"}, "2025-03-11": {"1. open": "106.99", "2. high": "112.236", "3. low": "104.77", "4. close": "108.76", "5. adjusted close": "108.750603887689", "6. volume": "354865692", "7. dividend amount": "0.0000", "8. split coefficient": "1.0"}, "2025-03-10": {"1. open": "109.9", "2. high": "111.85", "3. low": "105.46", "4. close": "106.98", "5. adjusted close": "106.970757667387", "6. volume": "361107562", "7. dividend amount": "0.0000", "8. split coefficient": "1.0"}, "2025-03-07": {"1. open": "111.25", "2. high": "113.48", "3. low": "107.56", "4. close": "112.69", "5. adjusted close": "112.680264362851", "6. volume": "341755468", "7. dividend amount": "0.0000", "8. split coefficient": "1.0"}, "2025-03-06": {"1. open": "113.53", "2. high": "115.35", "3. low": "110.22", "4. close": "110.57", "5. adjusted close": "110.560447516199", "6. volume": "321181861", "7. dividend amount": "0.0000", "8. split coefficient": "1.0"}, "2025-03-05": {"1. open": "117.58", "2. high": "118.2781", "3. low": "114.51", "4. close": "117.3", "5. adjusted close": "117.289866090713", "6. volume": "284337886", "7. dividend amount": "0.0000", "8. split coefficient": "1.0"}, "2025-03-04": {"1. open": "110.645", "2. high": "119.31", "3. low": "110.11", "4. close": "115.99", "5. adjusted close": "115.979979265659", "6. volume": "398163305", "7. dividend amount": "0.0000", "8. split coefficient": "1.0"}, "2025-03-03": {"1. open": "123.51", "2. high": "123.7", "3. low": "112.28", "4. close": "114.06", "5. adjusted close": "114.05014600432", "6. volume": "411381373", "7. dividend amount": "0.0000", "8. split coefficient": "1.0"}, "2025-02-28": {"1. open": "118.02", "2. high": "125.09", "3. low": "116.4", "4. close": "124.92", "5. adjusted close": "124.909207775378", "6. volume": "389091145", "7. dividend amount": "0.0000", "8. split coefficient": "1.0"}, "2025-02-27": {"1. open": "135.0", "2. high": "135.01", "3. low": "120.01", "4. close": "120.15", "5. adjusted close": "120.13961987041", "6. volume": "443175846", "7. dividend amount": "0.0000", "8. split coefficient": "1.0"}, "2025-02-26": {"1. open": "129.985", "2. high": "133.73", "3. low": "128.49", "4. close": "131.28", "5. adjusted close": "131.268658315335", "6. volume": "322553814", "7. dividend amount": "0.0000", "8. split coefficient": "1.0"}, "2025-02-25": {"1. open": "129.98", "2. high": "130.2", "3. low": "124.44", "4. close": "126.63", "5. adjusted close": "126.619060043197", "6. volume": "271428711", "7. dividend amount": "0.0000", "8. split coefficient": "1.0"}, "2025-02-24": {"1. open": "136.56", "2. high": "138.59", "3. low": "130.08", "4. close": "130.28", "5. adjusted close": "130.268744708423", "6. volume": "251381137", "7. dividend amount": "0.0000", "8. split coefficient": "1.0"}, "2025-02-21": {"1. open": "140.04", "2. high": "141.46", "3. low": "134.03", "4. close": "134.43", "5. adjusted close": "134.418386177106", "6. volume": "228217585", "7. dividend amount": "0.0000", "8. split coefficient": "1.0"}, "2025-02-20": {"1. open": "140.03", "2. high": "140.66", "3. low": "136.7901", "4. close": "140.11", "5. adjusted close": "140.097895464363", "6. volume": "143903583", "7. dividend amount": "0.0000", "8. split coefficient": "1.0"}, "2025-02-19": {"1. open": "139.51", "2. high": "141.36", "3. low": "137.22", "4. close": "139.23", "5. adjusted close": "139.217971490281", "6. volume": "167536006", "7. dividend amount": "0.0000", "8. split coefficient": "1.0"}, "2025-02-18": {"1. open": "141.27", "2. high": "143.44", "3. low": "137.925", "4. close": "139.4", "5. adjusted close": "139.387956803456", "6. volume": "219176627", "7. dividend amount": "0.0000", "8. split coefficient": "1.0"}, "2025-02-14": {"1. open": "136.48", "2. high": "139.25", "3. low": "135.5", "4. close": "138.85", "5. adjusted close": "138.838004319654", "6. volume": "195479557", "7. dividend amount": "0.0000", "8. split coefficient": "1.0"}, "2025-02-13": {"1. open": "131.555", "2. high": "136.5", "3. low": "131.17", "4. close": "135.29", "5. adjusted close": "135.27831187905", "6. volume": "197429975", "7. dividend amount": "0.0000", "8. split coefficient": "1.0"}, "2025-02-12": {"1. open": "130.02", "2. high": "132.24", "3. low": "129.08", "4. close": "131.14", "5. adjusted close": "131.128670410367", "6. volume": "160278552", "7. dividend amount": "0.0000", "8. split coefficient": "1.0"}, "2025-02-11": {"1. open": "132.58", "2. high": "134.48", "3. low": "131.02", "4. close": "132.8", "5. adjusted close": "132.78852699784", "6. volume": "178902379", "7. dividend amount": "0.0000", "8. split coefficient": "1.0"}, "2025-02-10": {"1. open": "130.09", "2. high": "135.0", "3. low": "129.96", "4. close": "133.57", "5. adjusted close": "133.558460475162", "6. volume": "216989086", "7. dividend amount": "0.0000", "8. split coefficient": "1.0"}, "2025-02-07": {"1. open": "129.22", "2. high": "130.37", "3. low": "125.0", "4. close": "129.84", "5. adjusted close": "129.828782721382", "6. volume": "228186298", "7. dividend amount": "0.0000", "8. split coefficient": "1.0"}, "2025-02-06": {"1. open": "127.42", "2. high": "128.77", "3. low": "125.21", "4. close": "128.68", "5. adjusted close": "128.668882937365", "6. volume": "251483574", "7. dividend amount": "0.0000", "8. split coefficient": "1.0"}, "2025-02-05": {"1. open": "121.76", "2. high": "125.0", "3. low": "120.76", "4. close": "124.83", "5. adjusted close": "124.819215550756", "6. volume": "263110629", "7. dividend amount": "0.0000", "8. split coefficient": "1.0"}, "2025-02-04": {"1. open": "116.96", "2. high": "121.2", "3. low": "116.7", "4. close": "118.65", "5. adjusted close": "118.639749460043", "6. volume": "256550040", "7. dividend amount": "0.0000", "8. split coefficient": "1.0"}, "2025-02-03": {"1. open": "114.75", "2. high": "118.57", "3. low": "113.01", "4. close": "116.66", "5. adjusted close": "116.649921382289", "6. volume": "371235677", "7. dividend amount": "0.0000", "8. split coefficient": "1.0"}, "2025-01-31": {"1. open": "123.78", "2. high": "127.85", "3. low": "119.19", "4. close": "120.07", "5. adjusted close": "120.059626781857", "6. volume": "390372899", "7. dividend amount": "0.0000", "8. split coefficient": "1.0"}, "2025-01-30": {"1. open": "123.1", "2. high": "125.0", "3. low": "118.1", "4. close": "124.65", "5. adjusted close": "124.639231101512", "6. volume": "392925469", "7. dividend amount": "0.0000", "8. split coefficient": "1.0"}, "2025-01-29": {"1. open": "126.5", "2. high": "126.89", "3. low": "120.05", "4. close": "123.7", "5. adjusted close": "123.689313174946", "6. volume": "467120640", "7. dividend amount": "0.0000", "8. split coefficient": "1.0"}, "2025-01-28": {"1. open": "121.81", "2. high": "129.0", "3. low": "116.25", "4. close": "128.99", "5. adjusted close": "128.978856155508", "6. volume": "579666350", "7. dividend amount": "0.0000", "8. split coefficient": "1.0"}, "2025-01-27": {"1. open": "124.8", "2. high": "128.4", "3. low": "116.7", "4. close": "118.42", "5. adjusted close": "118.409769330454", "6. volume": "818830895", "7. dividend amount": "0.0000", "8. split coefficient": "1.0"}, "2025-01-24": {"1. open": "148.37", "2. high": "148.97", "3. low": "141.88", "4. close": "142.62", "5. adjusted close": "142.607678617711", "6. volume": "234657635", "7. dividend amount": "0.0000", "8. split coefficient": "1.0"}, "2025-01-23": {"1. open": "145.05", "2. high": "147.23", "3. low": "143.72", "4. close": "147.22", "5. adjusted close": "147.207281209503", "6. volume": "155915549", "7. dividend amount": "0.0000", "8. split coefficient": "1.0"}, "2025-01-22": {"1. open": "144.66", "2. high": "147.79", "3. low": "143.67", "4. close": "147.07", "5. adjusted close": "147.057294168467", "6. volume": "237651395", "7. dividend amount": "0.0000", "8. split coefficient": "1.0"}, "2025-01-21": {"1. open": "139.16", "2. high": "141.83", "3. low": "137.09", "4. close": "140.83", "5. adjusted close": "140.817833261339", "6. volume": "197748985", "7. dividend amount": "0.0000", "8. split coefficient": "1.0"}, "2025-01-17": {"1. open": "136.69", "2. high": "138.5", "3. low": "135.4649", "4. close": "137.71", "5. adjusted close": "137.698102807775", "6. volume": "201188760", "7. dividend amount": "0.0000", "8. split coefficient": "1.0"}, "2025-01-16": {"1. open": "138.64", "2. high": "138.75", "3. low": "133.49", "4. close": "133.57", "5. adjusted close": "133.558460475162", "6. volume": "209235583", "7. dividend amount": "0.0000", "8. split coefficient": "1.0"}, "2025-01-15": {"1. open": "133.65", "2. high": "136.45", "3. low": "131.29", "4. close": "136.24", "5. adjusted close": "136.228229805616", "6. volume": "185217338", "7. dividend amount": "0.0000", "8. split coefficient": "1.0"}, "2025-01-14": {"1. open": "136.05", "2. high": "136.38", "3. low": "130.05", "4. close": "131.76", "5. adjusted close": "131.748616846652", "6. volume": "195590485", "7. dividend amount": "0.0000", "8. split coefficient": "1.0"}, "2025-01-13": {"1. open": "129.99", "2. high": "133.49", "3. low": "129.51", "4. close": "133.23", "5. adjusted close": "133.218489848812", "6. volume": "204808914", "7. dividend amount": "0.0000", "8. split coefficient": "1.0"}, "2025-01-10": {"1. open": "137.45", "2. high": "139.92", "3. low": "134.22", "4. close": "135.91", "5. adjusted close": "135.898258315335", "6. volume": "207602514", "7. dividend amount": "0.0000", "8. split coefficient": "1.0"}, "2025-01-08": {"1. open": "142.58", "2. high": "143.95", "3. low": "137.56", "4. close": "140.11", "5. adjusted close": "140.097895464363", "6. volume": "227349948", "7. dividend amount": "0.0000", "8. split coefficient": "1.0"}, "2025-01-07": {"1. open": "153.03", "2. high": "153.13", "3. low": "140.01", "4. close": "140.14", "5. adjusted close": "140.12789287257", "6. volume": "351782174", "7. dividend amount": "0.0000", "8. split coefficient": "1.0"}, "2025-01-06": {"1. open": "148.59", "2. high": "152.156", "3. low": "147.8201", "4. close": "149.43", "5. adjusted close": "149.417090280778", "6. volume": "265377359", "7. dividend amount": "0.0000", "8. split coefficient": "1.0"}, "2025-01-03": {"1. open": "140.01", "2. high": "144.9", "3. low": "139.73", "4. close": "144.47", "5. adjusted close": "144.457518790497", "6. volume": "229322478", "7. dividend amount": "0.0000", "8. split coefficient": "1.0"}, "2025-01-02": {"1. open": "136.0", "2. high": "138.88", "3. low": "134.63", "4. close": "138.31", "5. adjusted close": "138.298050971922", "6. volume": "198247166", "7. dividend amount": "0.0000", "8. split coefficient": "1.0"}, "2024-12-31": {"1. open": "138.03", "2. high": "138.07", "3. low": "133.83", "4. close": "134.29", "5. adjusted close": "134.278398272138", "6. volume": "155659211", "7. dividend amount": "0.0000", "8. split coefficient": "1.0"}, "2024-12-30": {"1. open": "134.83", "2. high": "140.27", "3. low": "134.02", "4. close": "137.49", "5. adjusted close": "137.478121814255", "6. volume": "167734700", "7. dividend amount": "0.0000", "8. split coefficient": "1.0"}, "2024-12-27": {"1. open": "138.55", "2. high": "139.02", "3. low": "134.71", "4. close": "137.01", "5. adjusted close": "136.998163282937", "6. volume": "170582603", "7. dividend amount": "0.0000", "8. split coefficient": "1.0"}, "2024-12-26": {"1. open": "139.7", "2. high": "140.85", "3. low": "137.73", "4. close": "139.93", "5. adjusted close": "139.917911015119", "6. volume": "116519090", "7. dividend amount": "0.0000", "8. split coefficient": "1.0"}, "2024-12-24": {"1. open": "140.0", "2. high": "141.9", "3. low": "138.65", "4. close": "140.22", "5. adjusted close": "140.207885961123", "6. volume": "105156989", "7. dividend amount": "0.0000", "8. split coefficient": "1.0"}, "2024-12-23": {"1. open": "136.28", "2. high": "139.79", "3. low": "135.1201", "4. close": "139.67", "5. adjusted close": "139.657933477322", "6. volume": "176053506", "7. dividend amount": "0.0000", "8. split coefficient": "1.0"}, "2024-12-20": {"1. open": "129.81", "2. high": "135.28", "3. low": "128.22", "4. close": "134.7", "5. adjusted close": "134.688362850972", "6. volume": "306528553", "7. dividend amount": "0.0000", "8. split coefficient": "1.0"}, "2024-12-19": {"1. open": "131.76", "2. high": "134.03", "3. low": "129.55", "4. close": "130.68", "5. adjusted close": "130.668710151188", "6. volume": "209719210", "7. dividend amount": "0.0000", "8. split coefficient": "1.0"}, "2024-12-18": {"1. open": "133.86", "2. high": "136.7", "3. low": "128.28", "4. close": "128.91", "5. adjusted close": "128.898863066955", "6. volume": "277444533", "7. dividend amount": "0.0000", "8. split coefficient": "1.0"}, "2024-12-17": {"1. open": "129.09", "2. high": "131.59", "3. low": "126.86", "4. close": "130.39", "5. adjusted close": "130.378735205184", "6. volume": "259410263", "7. dividend amount": "0.0000", "8. split coefficient": "1.0"}, "2024-12-16": {"1. open": "134.18", "2. high": "134.4", "3. low": "130.42", "4. close": "132.0", "5. adjusted close": "131.988596112311", "6. volume": "237951130", "7. dividend amount": "0.0000", "8. split coefficient": "1.0"}, "2024-12-13": {"1. open": "138.94", "2. high": "139.6", "3. low": "132.54", "4. close": "134.25", "5. adjusted close": "134.238401727862", "6. volume": "231514881", "7. dividend amount": "0.0000", "8. split coefficient": "1.0"}, "2024-12-12": {"1. open": "137.08", "2. high": "138.44", "3. low": "135.8", "4. close": "137.34", "5. adjusted close": "137.328134773218", "6. volume": "159211393", "7. dividend amount": "0.0000", "8. split coefficient": "1.0"}, "2024-12-11": {"1. open": "137.36", "2. high": "140.17", "3. low": "135.21", "4. close": "139.31", "5. adjusted close": "139.297964578834", "6. volume": "184905192", "7. dividend amount": "0.0000", "8. split coefficient": "1.0"}, "2024-12-10": {"1. open": "139.01", "2. high": "141.82", "3. low": "133.79", "4. close": "135.07", "5. adjusted close": "135.058330885529", "6. volume": "210020888", "7. dividend amount": "0.0000", "8. split coefficient": "1.0"}, "2024-12-09": {"1. open": "138.97", "2. high": "139.95", "3. low": "137.13", "4. close": "138.81", "5. adjusted close": "138.798007775378", "6. volume": "189308625", "7. dividend amount": "0.0000", "8. split coefficient": "1.0"}, "2024-12-06": {"1. open": "144.6", "2. high": "145.7", "3. low": "141.31", "4. close": "142.44", "5. adjusted close": "142.427694168467", "6. volume": "188505573", "7. dividend amount": "0.0000", "8. split coefficient": "1.0"}, "2024-12-05": {"1. open": "145.11", "2. high": "146.54", "3. low": "143.95", "4. close": "145.06", "5. adjusted close": "145.047467818575", "6. volume": "172621180", "7. dividend amount": "0.0100", "8. split coefficient": "1.0"}, "2024-12-04": {"1. open": "141.995", "2. high": "145.79", "3. low": "140.29", "4. close": "145.14", "5. adjusted close": "145.117456946218", "6. volume": "231224295", "7. dividend amount": "0.0000", "8. split coefficient": "1.0"}, "2024-12-03": {"1. open": "138.26", "2. high": "140.54", "3. low": "137.95", "4. close": "140.26", "5. adjusted close": "140.238214904758", "6. volume": "164413965", "7. dividend amount": "0.0000", "8. split coefficient": "1.0"}, "2024-12-02": {"1. open": "138.83", "2. high": "140.45", "3. low": "137.825", "4. close": "138.63", "5. adjusted close": "138.608468075336", "6. volume": "171682777", "7. dividend amount": "0.0000", "8. split coefficient": "1.0"}, "2024-11-29": {"1. open": "136.78", "2. high": "139.35", "3. low": "136.05", "4. close": "138.25", "5. adjusted close": "138.228527096698", "6. volume": "141863156", "7. dividend amount": "0.0000", "8. split coefficient": "1.0"}, "2024-11-27": {"1. open": "135.01", "2. high": "137.22", "3. low": "131.8", "4. close": "135.34", "5. adjusted close": "135.318979076073", "6. volume": "226370912", "7. dividend amount": "0.0000", "8. split coefficient": "1.0"}, "2024-11-26": {"1. open": "137.7", "2. high": "139.3", "3. low": "135.67", "4. close": "136.92", "5. adjusted close": "136.898733671464", "6. volume": "190287654", "7. dividend amount": "0.0000", "8. split coefficient": "1.0"}, "2024-11-25": {"1. open": "141.99", "2. high": "142.05", "3. low": "135.82", "4. close": "136.02", "5. adjusted close": "135.998873458899", "6. volume": "344941875", "7. dividend amount": "0.0000", "8. split coefficient": "1.0"}}}